<?xml version="1.0" encoding="ISO-8859-9"?>
<GTIPCODES>
	<GTIP>
		<CODE>07.01</CODE>
		<LEVEL_>2</LEVEL_>
		<CODEEMPTY>0</CODEEMPTY>
		<SELECTABLE>0</SELECTABLE>
		<DESCRIPTIONS>
			<DESCRIPTION>
				<INDEX_>1</INDEX_>
				<DESCR>Patates (taze veya soðutulmuþ):</DESCR>
			</DESCRIPTION>
		</DESCRIPTIONS>
	</GTIP>
	<GTIP>
		<CODE>07.01.10.00.00.00</CODE>
		<LEVEL_>3</LEVEL_>
		<CODEEMPTY>0</CODEEMPTY>
		<SELECTABLE>1</SELECTABLE>
		<DESCRIPTIONS>
			<DESCRIPTION>
				<INDEX_>1</INDEX_>
				<DESCR>Tohumluk</DESCR>
			</DESCRIPTION>
		</DESCRIPTIONS>
	</GTIP>
	<GTIP>
		<CODE>07.01.90</CODE>
		<LEVEL_>3</LEVEL_>
		<CODEEMPTY>0</CODEEMPTY>
		<SELECTABLE>0</SELECTABLE>
		<DESCRIPTIONS>
			<DESCRIPTION>
				<INDEX_>1</INDEX_>
				<DESCR>Diðerleri:</DESCR>
			</DESCRIPTION>
		</DESCRIPTIONS>
	</GTIP>
	<GTIP>
		<CODE>07.01.90.10.00.00</CODE>
		<LEVEL_>4</LEVEL_>
		<CODEEMPTY>0</CODEEMPTY>
		<SELECTABLE>1</SELECTABLE>
		<DESCRIPTIONS>
			<DESCRIPTION>
				<INDEX_>1</INDEX_>
				<DESCR>Niþasta imalinde kullanýlanlar</DESCR>
			</DESCRIPTION>
		</DESCRIPTIONS>
	</GTIP>
	<GTIP>
		<CODE>07.01.90.10.00.00.0</CODE>
		<LEVEL_>4</LEVEL_>
		<CODEEMPTY>1</CODEEMPTY>
		<SELECTABLE>0</SELECTABLE>
		<DESCRIPTIONS>
			<DESCRIPTION>
				<INDEX_>1</INDEX_>
				<DESCR>Diðerleri:</DESCR>
			</DESCRIPTION>
		</DESCRIPTIONS>
	</GTIP>
	<GTIP>
		<CODE>07.01.90.50.00.00</CODE>
		<LEVEL_>5</LEVEL_>
		<CODEEMPTY>0</CODEEMPTY>
		<SELECTABLE>1</SELECTABLE>
		<DESCRIPTIONS>
			<DESCRIPTION>
				<INDEX_>1</INDEX_>
				<DESCR>Taze (1 Ocak'tan 30 Haziran'a kadar olanlar)</DESCR>
			</DESCRIPTION>
		</DESCRIPTIONS>
	</GTIP>
	<GTIP>
		<CODE>07.01.90.90.00.00</CODE>
		<LEVEL_>5</LEVEL_>
		<CODEEMPTY>0</CODEEMPTY>
		<SELECTABLE>1</SELECTABLE>
		<DESCRIPTIONS>
			<DESCRIPTION>
				<INDEX_>1</INDEX_>
				<DESCR>Diðerleri</DESCR>
			</DESCRIPTION>
		</DESCRIPTIONS>
	</GTIP>
	<GTIP>
		<CODE>07.02.00.00.00.00</CODE>
		<LEVEL_>2</LEVEL_>
		<CODEEMPTY>0</CODEEMPTY>
		<SELECTABLE>1</SELECTABLE>
		<DESCRIPTIONS>
			<DESCRIPTION>
				<INDEX_>1</INDEX_>
				<DESCR>Domates (taze veya soðutulmuþ)</DESCR>
			</DESCRIPTION>
		</DESCRIPTIONS>
	</GTIP>
	<GTIP>
		<CODE>07.03</CODE>
		<LEVEL_>2</LEVEL_>
		<CODEEMPTY>0</CODEEMPTY>
		<SELECTABLE>0</SELECTABLE>
		<DESCRIPTIONS>
			<DESCRIPTION>
				<INDEX_>1</INDEX_>
				<DESCR>Soðanlar, þalotlar, sarýmsaklar, pýrasalar ve diðer soðanýmsý sebzeler (taze veya soðutulmuþ):</DESCR>
			</DESCRIPTION>
		</DESCRIPTIONS>
	</GTIP>
	<GTIP>
		<CODE>07.03.10</CODE>
		<LEVEL_>3</LEVEL_>
		<CODEEMPTY>0</CODEEMPTY>
		<SELECTABLE>0</SELECTABLE>
		<DESCRIPTIONS>
			<DESCRIPTION>
				<INDEX_>1</INDEX_>
				<DESCR>Soðanlar ve þalotlar:</DESCR>
			</DESCRIPTION>
		</DESCRIPTIONS>
	</GTIP>
	<GTIP>
		<CODE>07.03.10.0</CODE>
		<LEVEL_>4</LEVEL_>
		<CODEEMPTY>1</CODEEMPTY>
		<SELECTABLE>0</SELECTABLE>
		<DESCRIPTIONS>
			<DESCRIPTION>
				<INDEX_>1</INDEX_>
				<DESCR>Soðanlar:</DESCR>
			</DESCRIPTION>
		</DESCRIPTIONS>
	</GTIP>
	<GTIP>
		<CODE>07.03.10.11.00.00</CODE>
		<LEVEL_>5</LEVEL_>
		<CODEEMPTY>0</CODEEMPTY>
		<SELECTABLE>1</SELECTABLE>
		<DESCRIPTIONS>
			<DESCRIPTION>
				<INDEX_>1</INDEX_>
				<DESCR>Arpacýk soðaný</DESCR>
			</DESCRIPTION>
		</DESCRIPTIONS>
	</GTIP>
	<GTIP>
		<CODE>07.03.10.11.00.00.0</CODE>
		<LEVEL_>5</LEVEL_>
		<CODEEMPTY>1</CODEEMPTY>
		<SELECTABLE>0</SELECTABLE>
		<DESCRIPTIONS>
			<DESCRIPTION>
				<INDEX_>1</INDEX_>
				<DESCR>Diðerleri</DESCR>
			</DESCRIPTION>
		</DESCRIPTIONS>
	</GTIP>
	<GTIP>
		<CODE>07.03.10.19.00.11</CODE>
		<LEVEL_>6</LEVEL_>
		<CODEEMPTY>0</CODEEMPTY>
		<SELECTABLE>1</SELECTABLE>
		<DESCRIPTIONS>
			<DESCRIPTION>
				<INDEX_>1</INDEX_>
				<DESCR>Kuru soðan</DESCR>
			</DESCRIPTION>
		</DESCRIPTIONS>
	</GTIP>
	<GTIP>
		<CODE>07.03.10.19.00.12</CODE>
		<LEVEL_>6</LEVEL_>
		<CODEEMPTY>0</CODEEMPTY>
		<SELECTABLE>1</SELECTABLE>
		<DESCRIPTIONS>
			<DESCRIPTION>
				<INDEX_>1</INDEX_>
				<DESCR>Taze soðan</DESCR>
			</DESCRIPTION>
		</DESCRIPTIONS>
	</GTIP>
	<GTIP>
		<CODE>07.03.10.90.00.00</CODE>
		<LEVEL_>4</LEVEL_>
		<CODEEMPTY>0</CODEEMPTY>
		<SELECTABLE>1</SELECTABLE>
		<DESCRIPTIONS>
			<DESCRIPTION>
				<INDEX_>1</INDEX_>
				<DESCR>Þalotlar</DESCR>
			</DESCRIPTION>
		</DESCRIPTIONS>
	</GTIP>
	<GTIP>
		<CODE>07.03.20</CODE>
		<LEVEL_>3</LEVEL_>
		<CODEEMPTY>0</CODEEMPTY>
		<SELECTABLE>0</SELECTABLE>
		<DESCRIPTIONS>
			<DESCRIPTION>
				<INDEX_>1</INDEX_>
				<DESCR>Sarýmsaklar:</DESCR>
			</DESCRIPTION>
		</DESCRIPTIONS>
	</GTIP>
	<GTIP>
		<CODE>07.03.20.00.00.11</CODE>
		<LEVEL_>4</LEVEL_>
		<CODEEMPTY>0</CODEEMPTY>
		<SELECTABLE>1</SELECTABLE>
		<DESCRIPTIONS>
			<DESCRIPTION>
				<INDEX_>1</INDEX_>
				<DESCR>Taze sarýmsak</DESCR>
			</DESCRIPTION>
		</DESCRIPTIONS>
	</GTIP>
	<GTIP>
		<CODE>07.03.20.00.00.12</CODE>
		<LEVEL_>4</LEVEL_>
		<CODEEMPTY>0</CODEEMPTY>
		<SELECTABLE>1</SELECTABLE>
		<DESCRIPTIONS>
			<DESCRIPTION>
				<INDEX_>1</INDEX_>
				<DESCR>Kuru sarýmsak</DESCR>
			</DESCRIPTION>
		</DESCRIPTIONS>
	</GTIP>
	<GTIP>
		<CODE>07.03.90</CODE>
		<LEVEL_>3</LEVEL_>
		<CODEEMPTY>0</CODEEMPTY>
		<SELECTABLE>0</SELECTABLE>
		<DESCRIPTIONS>
			<DESCRIPTION>
				<INDEX_>1</INDEX_>
				<DESCR>Pýrasa ve diðer soðanýmsý sebzeler:</DESCR>
			</DESCRIPTION>
		</DESCRIPTIONS>
	</GTIP>
	<GTIP>
		<CODE>07.03.90.00.00.11</CODE>
		<LEVEL_>4</LEVEL_>
		<CODEEMPTY>0</CODEEMPTY>
		<SELECTABLE>1</SELECTABLE>
		<DESCRIPTIONS>
			<DESCRIPTION>
				<INDEX_>1</INDEX_>
				<DESCR>Pýrasa</DESCR>
			</DESCRIPTION>
		</DESCRIPTIONS>
	</GTIP>
	<GTIP>
		<CODE>07.03.90.00.00.12</CODE>
		<LEVEL_>4</LEVEL_>
		<CODEEMPTY>0</CODEEMPTY>
		<SELECTABLE>1</SELECTABLE>
		<DESCRIPTIONS>
			<DESCRIPTION>
				<INDEX_>1</INDEX_>
				<DESCR>Soðanýmsý sebzeler</DESCR>
			</DESCRIPTION>
		</DESCRIPTIONS>
	</GTIP>
	<GTIP>
		<CODE>07.04</CODE>
		<LEVEL_>2</LEVEL_>
		<CODEEMPTY>0</CODEEMPTY>
		<SELECTABLE>0</SELECTABLE>
		<DESCRIPTIONS>
			<DESCRIPTION>
				<INDEX_>1</INDEX_>
				<DESCR>Lahanalar, karnabaharlar, alabaþlar, yaprak lahanalar ve benzeri yenilen brassikalar (taze veya soðutulmuþ):</DESCR>
			</DESCRIPTION>
		</DESCRIPTIONS>
	</GTIP>
	<GTIP>
		<CODE>07.04.10</CODE>
		<LEVEL_>3</LEVEL_>
		<CODEEMPTY>0</CODEEMPTY>
		<SELECTABLE>0</SELECTABLE>
		<DESCRIPTIONS>
			<DESCRIPTION>
				<INDEX_>1</INDEX_>
				<DESCR>Karnabaharlar ve baþlý brokoli</DESCR>
			</DESCRIPTION>
		</DESCRIPTIONS>
	</GTIP>
	<GTIP>
		<CODE>07.04.10.00.00.11</CODE>
		<LEVEL_>4</LEVEL_>
		<CODEEMPTY>0</CODEEMPTY>
		<SELECTABLE>1</SELECTABLE>
		<DESCRIPTIONS>
			<DESCRIPTION>
				<INDEX_>1</INDEX_>
				<DESCR>Karnabahar</DESCR>
			</DESCRIPTION>
		</DESCRIPTIONS>
	</GTIP>
	<GTIP>
		<CODE>07.04.10.00.00.12</CODE>
		<LEVEL_>4</LEVEL_>
		<CODEEMPTY>0</CODEEMPTY>
		<SELECTABLE>1</SELECTABLE>
		<DESCRIPTIONS>
			<DESCRIPTION>
				<INDEX_>1</INDEX_>
				<DESCR>Brokoli</DESCR>
			</DESCRIPTION>
		</DESCRIPTIONS>
	</GTIP>
	<GTIP>
		<CODE>07.04.20.00.00.00</CODE>
		<LEVEL_>3</LEVEL_>
		<CODEEMPTY>0</CODEEMPTY>
		<SELECTABLE>1</SELECTABLE>
		<DESCRIPTIONS>
			<DESCRIPTION>
				<INDEX_>1</INDEX_>
				<DESCR>Brüksel lahanasý</DESCR>
			</DESCRIPTION>
		</DESCRIPTIONS>
	</GTIP>
	<GTIP>
		<CODE>07.04.90</CODE>
		<LEVEL_>3</LEVEL_>
		<CODEEMPTY>0</CODEEMPTY>
		<SELECTABLE>0</SELECTABLE>
		<DESCRIPTIONS>
			<DESCRIPTION>
				<INDEX_>1</INDEX_>
				<DESCR>Diðerleri:</DESCR>
			</DESCRIPTION>
		</DESCRIPTIONS>
	</GTIP>
	<GTIP>
		<CODE>07.04.90.0</CODE>
		<LEVEL_>4</LEVEL_>
		<CODEEMPTY>1</CODEEMPTY>
		<SELECTABLE>0</SELECTABLE>
		<DESCRIPTIONS>
			<DESCRIPTION>
				<INDEX_>1</INDEX_>
				<DESCR>Beyaz lahana ve kýrmýzý lahana</DESCR>
			</DESCRIPTION>
		</DESCRIPTIONS>
	</GTIP>
	<GTIP>
		<CODE>07.04.90.10.00.11</CODE>
		<LEVEL_>5</LEVEL_>
		<CODEEMPTY>0</CODEEMPTY>
		<SELECTABLE>1</SELECTABLE>
		<DESCRIPTIONS>
			<DESCRIPTION>
				<INDEX_>1</INDEX_>
				<DESCR>Beyaz lahana</DESCR>
			</DESCRIPTION>
		</DESCRIPTIONS>
	</GTIP>
	<GTIP>
		<CODE>07.04.90.10.00.12</CODE>
		<LEVEL_>5</LEVEL_>
		<CODEEMPTY>0</CODEEMPTY>
		<SELECTABLE>1</SELECTABLE>
		<DESCRIPTIONS>
			<DESCRIPTION>
				<INDEX_>1</INDEX_>
				<DESCR>Kýrmýzý lahana</DESCR>
			</DESCRIPTION>
		</DESCRIPTIONS>
	</GTIP>
	<GTIP>
		<CODE>07.04.90.90.00.00</CODE>
		<LEVEL_>4</LEVEL_>
		<CODEEMPTY>0</CODEEMPTY>
		<SELECTABLE>1</SELECTABLE>
		<DESCRIPTIONS>
			<DESCRIPTION>
				<INDEX_>1</INDEX_>
				<DESCR>Diðerleri</DESCR>
			</DESCRIPTION>
		</DESCRIPTIONS>
	</GTIP>
	<GTIP>
		<CODE>07.05</CODE>
		<LEVEL_>2</LEVEL_>
		<CODEEMPTY>0</CODEEMPTY>
		<SELECTABLE>0</SELECTABLE>
		<DESCRIPTIONS>
			<DESCRIPTION>
				<INDEX_>1</INDEX_>
				<DESCR>Marul ( Lactuca sativa) ve hindiba (Cichorium spp.) (taze veya soðutulmuþ) :</DESCR>
			</DESCRIPTION>
		</DESCRIPTIONS>
	</GTIP>
	<GTIP>
		<CODE>07.05.0</CODE>
		<LEVEL_>3</LEVEL_>
		<CODEEMPTY>1</CODEEMPTY>
		<SELECTABLE>0</SELECTABLE>
		<DESCRIPTIONS>
			<DESCRIPTION>
				<INDEX_>1</INDEX_>
				<DESCR>Marul :</DESCR>
			</DESCRIPTION>
		</DESCRIPTIONS>
	</GTIP>
	<GTIP>
		<CODE>07.05.11.00.00.00</CODE>
		<LEVEL_>4</LEVEL_>
		<CODEEMPTY>0</CODEEMPTY>
		<SELECTABLE>1</SELECTABLE>
		<DESCRIPTIONS>
			<DESCRIPTION>
				<INDEX_>1</INDEX_>
				<DESCR>Baþ marul</DESCR>
			</DESCRIPTION>
		</DESCRIPTIONS>
	</GTIP>
	<GTIP>
		<CODE>07.05.19.00.00.00</CODE>
		<LEVEL_>4</LEVEL_>
		<CODEEMPTY>0</CODEEMPTY>
		<SELECTABLE>1</SELECTABLE>
		<DESCRIPTIONS>
			<DESCRIPTION>
				<INDEX_>1</INDEX_>
				<DESCR>Diðerleri</DESCR>
			</DESCRIPTION>
		</DESCRIPTIONS>
	</GTIP>
	<GTIP>
		<CODE>07.05.19.00.00.00.0</CODE>
		<LEVEL_>3</LEVEL_>
		<CODEEMPTY>1</CODEEMPTY>
		<SELECTABLE>0</SELECTABLE>
		<DESCRIPTIONS>
			<DESCRIPTION>
				<INDEX_>1</INDEX_>
				<DESCR>Hindiba:</DESCR>
			</DESCRIPTION>
		</DESCRIPTIONS>
	</GTIP>
	<GTIP>
		<CODE>07.05.21.00.00.00</CODE>
		<LEVEL_>4</LEVEL_>
		<CODEEMPTY>0</CODEEMPTY>
		<SELECTABLE>1</SELECTABLE>
		<DESCRIPTIONS>
			<DESCRIPTION>
				<INDEX_>1</INDEX_>
				<DESCR>Baþlý hindiba (Cichorium intybus var. folioeum)</DESCR>
			</DESCRIPTION>
		</DESCRIPTIONS>
	</GTIP>
	<GTIP>
		<CODE>07.05.29.00.00.00</CODE>
		<LEVEL_>4</LEVEL_>
		<CODEEMPTY>0</CODEEMPTY>
		<SELECTABLE>1</SELECTABLE>
		<DESCRIPTIONS>
			<DESCRIPTION>
				<INDEX_>1</INDEX_>
				<DESCR>Diðerleri</DESCR>
			</DESCRIPTION>
		</DESCRIPTIONS>
	</GTIP>
	<GTIP>
		<CODE>07.06</CODE>
		<LEVEL_>2</LEVEL_>
		<CODEEMPTY>0</CODEEMPTY>
		<SELECTABLE>0</SELECTABLE>
		<DESCRIPTIONS>
			<DESCRIPTION>
				<INDEX_>1</INDEX_>
				<DESCR>Havuçlar, þalgamlar, kýrmýzý pancar, teke sakalý (salsifis), kök kerevizi, turplar ve benzeri yenilen kökler (taze veya soðutulmuþ):</DESCR>
			</DESCRIPTION>
		</DESCRIPTIONS>
	</GTIP>
	<GTIP>
		<CODE>07.06.10</CODE>
		<LEVEL_>3</LEVEL_>
		<CODEEMPTY>0</CODEEMPTY>
		<SELECTABLE>0</SELECTABLE>
		<DESCRIPTIONS>
			<DESCRIPTION>
				<INDEX_>1</INDEX_>
				<DESCR>Havuçlar ve þalgamlar</DESCR>
			</DESCRIPTION>
		</DESCRIPTIONS>
	</GTIP>
	<GTIP>
		<CODE>07.06.10.00.00.11</CODE>
		<LEVEL_>4</LEVEL_>
		<CODEEMPTY>0</CODEEMPTY>
		<SELECTABLE>1</SELECTABLE>
		<DESCRIPTIONS>
			<DESCRIPTION>
				<INDEX_>1</INDEX_>
				<DESCR>Havuçlar</DESCR>
			</DESCRIPTION>
		</DESCRIPTIONS>
	</GTIP>
	<GTIP>
		<CODE>07.06.10.00.00.12</CODE>
		<LEVEL_>4</LEVEL_>
		<CODEEMPTY>0</CODEEMPTY>
		<SELECTABLE>1</SELECTABLE>
		<DESCRIPTIONS>
			<DESCRIPTION>
				<INDEX_>1</INDEX_>
				<DESCR>Þalgamlar</DESCR>
			</DESCRIPTION>
		</DESCRIPTIONS>
	</GTIP>
	<GTIP>
		<CODE>07.06.90</CODE>
		<LEVEL_>3</LEVEL_>
		<CODEEMPTY>0</CODEEMPTY>
		<SELECTABLE>0</SELECTABLE>
		<DESCRIPTIONS>
			<DESCRIPTION>
				<INDEX_>1</INDEX_>
				<DESCR>Diðerleri :</DESCR>
			</DESCRIPTION>
		</DESCRIPTIONS>
	</GTIP>
	<GTIP>
		<CODE>07.06.90.10.00.00</CODE>
		<LEVEL_>4</LEVEL_>
		<CODEEMPTY>0</CODEEMPTY>
		<SELECTABLE>1</SELECTABLE>
		<DESCRIPTIONS>
			<DESCRIPTION>
				<INDEX_>1</INDEX_>
				<DESCR>Kök kerevizi</DESCR>
			</DESCRIPTION>
		</DESCRIPTIONS>
	</GTIP>
	<GTIP>
		<CODE>07.06.90.30.00.00</CODE>
		<LEVEL_>4</LEVEL_>
		<CODEEMPTY>0</CODEEMPTY>
		<SELECTABLE>1</SELECTABLE>
		<DESCRIPTIONS>
			<DESCRIPTION>
				<INDEX_>1</INDEX_>
				<DESCR>Bayýr turbu (Cochlearia armoracia)</DESCR>
			</DESCRIPTION>
		</DESCRIPTIONS>
	</GTIP>
	<GTIP>
		<CODE>07.06.90.90.00.00</CODE>
		<LEVEL_>4</LEVEL_>
		<CODEEMPTY>0</CODEEMPTY>
		<SELECTABLE>1</SELECTABLE>
		<DESCRIPTIONS>
			<DESCRIPTION>
				<INDEX_>1</INDEX_>
				<DESCR>Diðerleri</DESCR>
			</DESCRIPTION>
		</DESCRIPTIONS>
	</GTIP>
	<GTIP>
		<CODE>07.07.00</CODE>
		<LEVEL_>2</LEVEL_>
		<CODEEMPTY>0</CODEEMPTY>
		<SELECTABLE>0</SELECTABLE>
		<DESCRIPTIONS>
			<DESCRIPTION>
				<INDEX_>1</INDEX_>
				<DESCR>Hýyarlar ve korniþonlar (taze veya soðutulmuþ) :</DESCR>
			</DESCRIPTION>
		</DESCRIPTIONS>
	</GTIP>
	<GTIP>
		<CODE>07.07.00.05.00.00</CODE>
		<LEVEL_>3</LEVEL_>
		<CODEEMPTY>0</CODEEMPTY>
		<SELECTABLE>1</SELECTABLE>
		<DESCRIPTIONS>
			<DESCRIPTION>
				<INDEX_>1</INDEX_>
				<DESCR>Hýyarlar</DESCR>
			</DESCRIPTION>
		</DESCRIPTIONS>
	</GTIP>
	<GTIP>
		<CODE>07.07.00.90.00.00</CODE>
		<LEVEL_>3</LEVEL_>
		<CODEEMPTY>0</CODEEMPTY>
		<SELECTABLE>1</SELECTABLE>
		<DESCRIPTIONS>
			<DESCRIPTION>
				<INDEX_>1</INDEX_>
				<DESCR>Korniþonlar</DESCR>
			</DESCRIPTION>
		</DESCRIPTIONS>
	</GTIP>
	<GTIP>
		<CODE>07.08</CODE>
		<LEVEL_>2</LEVEL_>
		<CODEEMPTY>0</CODEEMPTY>
		<SELECTABLE>0</SELECTABLE>
		<DESCRIPTIONS>
			<DESCRIPTION>
				<INDEX_>1</INDEX_>
				<DESCR>Baklagiller (kabuklu veya kabuksuz) (taze veya soðutulmuþ):</DESCR>
			</DESCRIPTION>
		</DESCRIPTIONS>
	</GTIP>
	<GTIP>
		<CODE>07.08.10</CODE>
		<LEVEL_>3</LEVEL_>
		<CODEEMPTY>0</CODEEMPTY>
		<SELECTABLE>0</SELECTABLE>
		<DESCRIPTIONS>
			<DESCRIPTION>
				<INDEX_>1</INDEX_>
				<DESCR>Bezelye (Pisum sativum)</DESCR>
			</DESCRIPTION>
		</DESCRIPTIONS>
	</GTIP>
	<GTIP>
		<CODE>07.08.10.00.00.11</CODE>
		<LEVEL_>4</LEVEL_>
		<CODEEMPTY>0</CODEEMPTY>
		<SELECTABLE>1</SELECTABLE>
		<DESCRIPTIONS>
			<DESCRIPTION>
				<INDEX_>1</INDEX_>
				<DESCR>Kabuklu</DESCR>
			</DESCRIPTION>
		</DESCRIPTIONS>
	</GTIP>
	<GTIP>
		<CODE>07.08.10.00.00.12</CODE>
		<LEVEL_>4</LEVEL_>
		<CODEEMPTY>0</CODEEMPTY>
		<SELECTABLE>1</SELECTABLE>
		<DESCRIPTIONS>
			<DESCRIPTION>
				<INDEX_>1</INDEX_>
				<DESCR>Kabuksuz</DESCR>
			</DESCRIPTION>
		</DESCRIPTIONS>
	</GTIP>
	<GTIP>
		<CODE>07.08.20</CODE>
		<LEVEL_>3</LEVEL_>
		<CODEEMPTY>0</CODEEMPTY>
		<SELECTABLE>0</SELECTABLE>
		<DESCRIPTIONS>
			<DESCRIPTION>
				<INDEX_>1</INDEX_>
				<DESCR>Fasulye (Vigna spp., Phaseotus spp.)</DESCR>
			</DESCRIPTION>
		</DESCRIPTIONS>
	</GTIP>
	<GTIP>
		<CODE>07.08.20.00.00.11</CODE>
		<LEVEL_>4</LEVEL_>
		<CODEEMPTY>0</CODEEMPTY>
		<SELECTABLE>1</SELECTABLE>
		<DESCRIPTIONS>
			<DESCRIPTION>
				<INDEX_>1</INDEX_>
				<DESCR>Fasulye</DESCR>
			</DESCRIPTION>
		</DESCRIPTIONS>
	</GTIP>
	<GTIP>
		<CODE>07.08.20.00.00.12</CODE>
		<LEVEL_>4</LEVEL_>
		<CODEEMPTY>0</CODEEMPTY>
		<SELECTABLE>1</SELECTABLE>
		<DESCRIPTIONS>
			<DESCRIPTION>
				<INDEX_>1</INDEX_>
				<DESCR>Barbunya (kabuklu)</DESCR>
			</DESCRIPTION>
		</DESCRIPTIONS>
	</GTIP>
	<GTIP>
		<CODE>07.08.20.00.00.13</CODE>
		<LEVEL_>4</LEVEL_>
		<CODEEMPTY>0</CODEEMPTY>
		<SELECTABLE>1</SELECTABLE>
		<DESCRIPTIONS>
			<DESCRIPTION>
				<INDEX_>1</INDEX_>
				<DESCR>Barbunya (kabuksuz)</DESCR>
			</DESCRIPTION>
		</DESCRIPTIONS>
	</GTIP>
	<GTIP>
		<CODE>07.08.90</CODE>
		<LEVEL_>3</LEVEL_>
		<CODEEMPTY>0</CODEEMPTY>
		<SELECTABLE>0</SELECTABLE>
		<DESCRIPTIONS>
			<DESCRIPTION>
				<INDEX_>1</INDEX_>
				<DESCR>Diðer baklagiller</DESCR>
			</DESCRIPTION>
		</DESCRIPTIONS>
	</GTIP>
	<GTIP>
		<CODE>07.08.90.00.00.11</CODE>
		<LEVEL_>4</LEVEL_>
		<CODEEMPTY>0</CODEEMPTY>
		<SELECTABLE>1</SELECTABLE>
		<DESCRIPTIONS>
			<DESCRIPTION>
				<INDEX_>1</INDEX_>
				<DESCR>Kabuklu baklagiller</DESCR>
			</DESCRIPTION>
		</DESCRIPTIONS>
	</GTIP>
	<GTIP>
		<CODE>07.08.90.00.00.12</CODE>
		<LEVEL_>4</LEVEL_>
		<CODEEMPTY>0</CODEEMPTY>
		<SELECTABLE>1</SELECTABLE>
		<DESCRIPTIONS>
			<DESCRIPTION>
				<INDEX_>1</INDEX_>
				<DESCR>Kabuksuz baklagiller</DESCR>
			</DESCRIPTION>
		</DESCRIPTIONS>
	</GTIP>
	<GTIP>
		<CODE>07.09</CODE>
		<LEVEL_>2</LEVEL_>
		<CODEEMPTY>0</CODEEMPTY>
		<SELECTABLE>0</SELECTABLE>
		<DESCRIPTIONS>
			<DESCRIPTION>
				<INDEX_>1</INDEX_>
				<DESCR>Diðer sebzeler(taze veya soðutulmuþ):</DESCR>
			</DESCRIPTION>
		</DESCRIPTIONS>
	</GTIP>
	<GTIP>
		<CODE>07.09.20.00.00.00</CODE>
		<LEVEL_>3</LEVEL_>
		<CODEEMPTY>0</CODEEMPTY>
		<SELECTABLE>1</SELECTABLE>
		<DESCRIPTIONS>
			<DESCRIPTION>
				<INDEX_>1</INDEX_>
				<DESCR>Kuþkonmazlar</DESCR>
			</DESCRIPTION>
		</DESCRIPTIONS>
	</GTIP>
	<GTIP>
		<CODE>07.09.30.00.00.00</CODE>
		<LEVEL_>3</LEVEL_>
		<CODEEMPTY>0</CODEEMPTY>
		<SELECTABLE>1</SELECTABLE>
		<DESCRIPTIONS>
			<DESCRIPTION>
				<INDEX_>1</INDEX_>
				<DESCR>Patlýcanlar</DESCR>
			</DESCRIPTION>
		</DESCRIPTIONS>
	</GTIP>
	<GTIP>
		<CODE>07.09.40.00.00.00</CODE>
		<LEVEL_>3</LEVEL_>
		<CODEEMPTY>0</CODEEMPTY>
		<SELECTABLE>1</SELECTABLE>
		<DESCRIPTIONS>
			<DESCRIPTION>
				<INDEX_>1</INDEX_>
				<DESCR>Yaprak kerevizleri (kök kerevizleri hariç)</DESCR>
			</DESCRIPTION>
		</DESCRIPTIONS>
	</GTIP>
	<GTIP>
		<CODE>07.09.40.00.00.00.0</CODE>
		<LEVEL_>3</LEVEL_>
		<CODEEMPTY>1</CODEEMPTY>
		<SELECTABLE>0</SELECTABLE>
		<DESCRIPTIONS>
			<DESCRIPTION>
				<INDEX_>1</INDEX_>
				<DESCR>Mantarlar ve domalanlar:</DESCR>
			</DESCRIPTION>
		</DESCRIPTIONS>
	</GTIP>
	<GTIP>
		<CODE>07.09.51.00.00.00</CODE>
		<LEVEL_>4</LEVEL_>
		<CODEEMPTY>0</CODEEMPTY>
		<SELECTABLE>1</SELECTABLE>
		<DESCRIPTIONS>
			<DESCRIPTION>
				<INDEX_>1</INDEX_>
				<DESCR>Agaricus cinsi mantarlar</DESCR>
			</DESCRIPTION>
		</DESCRIPTIONS>
	</GTIP>
	<GTIP>
		<CODE>07.09.59</CODE>
		<LEVEL_>4</LEVEL_>
		<CODEEMPTY>0</CODEEMPTY>
		<SELECTABLE>0</SELECTABLE>
		<DESCRIPTIONS>
			<DESCRIPTION>
				<INDEX_>1</INDEX_>
				<DESCR>Diðerleri</DESCR>
			</DESCRIPTION>
		</DESCRIPTIONS>
	</GTIP>
	<GTIP>
		<CODE>07.09.59.10.00.00</CODE>
		<LEVEL_>5</LEVEL_>
		<CODEEMPTY>0</CODEEMPTY>
		<SELECTABLE>1</SELECTABLE>
		<DESCRIPTIONS>
			<DESCRIPTION>
				<INDEX_>1</INDEX_>
				<DESCR>Cüce kýz mantarý (Chanterelles)</DESCR>
			</DESCRIPTION>
		</DESCRIPTIONS>
	</GTIP>
	<GTIP>
		<CODE>07.09.59.30.00.00</CODE>
		<LEVEL_>5</LEVEL_>
		<CODEEMPTY>0</CODEEMPTY>
		<SELECTABLE>1</SELECTABLE>
		<DESCRIPTIONS>
			<DESCRIPTION>
				<INDEX_>1</INDEX_>
				<DESCR>Kuzu mantarlarý</DESCR>
			</DESCRIPTION>
		</DESCRIPTIONS>
	</GTIP>
	<GTIP>
		<CODE>07.09.59.50.00.00</CODE>
		<LEVEL_>5</LEVEL_>
		<CODEEMPTY>0</CODEEMPTY>
		<SELECTABLE>1</SELECTABLE>
		<DESCRIPTIONS>
			<DESCRIPTION>
				<INDEX_>1</INDEX_>
				<DESCR>Yer mantarý (domalan)</DESCR>
			</DESCRIPTION>
		</DESCRIPTIONS>
	</GTIP>
	<GTIP>
		<CODE>07.09.59.90.00.00</CODE>
		<LEVEL_>5</LEVEL_>
		<CODEEMPTY>0</CODEEMPTY>
		<SELECTABLE>1</SELECTABLE>
		<DESCRIPTIONS>
			<DESCRIPTION>
				<INDEX_>1</INDEX_>
				<DESCR>Diðerleri</DESCR>
			</DESCRIPTION>
		</DESCRIPTIONS>
	</GTIP>
	<GTIP>
		<CODE>07.09.60</CODE>
		<LEVEL_>3</LEVEL_>
		<CODEEMPTY>0</CODEEMPTY>
		<SELECTABLE>0</SELECTABLE>
		<DESCRIPTIONS>
			<DESCRIPTION>
				<INDEX_>1</INDEX_>
				<DESCR>Capsicum veya Pimenta cinsi meyveler:</DESCR>
			</DESCRIPTION>
		</DESCRIPTIONS>
	</GTIP>
	<GTIP>
		<CODE>07.09.60.0</CODE>
		<LEVEL_>4</LEVEL_>
		<CODEEMPTY>1</CODEEMPTY>
		<SELECTABLE>0</SELECTABLE>
		<DESCRIPTIONS>
			<DESCRIPTION>
				<INDEX_>1</INDEX_>
				<DESCR>Tatlý (Capsicum grossum) biberler</DESCR>
			</DESCRIPTION>
		</DESCRIPTIONS>
	</GTIP>
	<GTIP>
		<CODE>07.09.60.10.00.11</CODE>
		<LEVEL_>5</LEVEL_>
		<CODEEMPTY>0</CODEEMPTY>
		<SELECTABLE>1</SELECTABLE>
		<DESCRIPTIONS>
			<DESCRIPTION>
				<INDEX_>1</INDEX_>
				<DESCR>Sivri biber</DESCR>
			</DESCRIPTION>
		</DESCRIPTIONS>
	</GTIP>
	<GTIP>
		<CODE>07.09.60.10.00.12</CODE>
		<LEVEL_>5</LEVEL_>
		<CODEEMPTY>0</CODEEMPTY>
		<SELECTABLE>1</SELECTABLE>
		<DESCRIPTIONS>
			<DESCRIPTION>
				<INDEX_>1</INDEX_>
				<DESCR>Dolmalýk biber</DESCR>
			</DESCRIPTION>
		</DESCRIPTIONS>
	</GTIP>
	<GTIP>
		<CODE>07.09.60.10.00.13</CODE>
		<LEVEL_>5</LEVEL_>
		<CODEEMPTY>0</CODEEMPTY>
		<SELECTABLE>1</SELECTABLE>
		<DESCRIPTIONS>
			<DESCRIPTION>
				<INDEX_>1</INDEX_>
				<DESCR>Çarliston biber</DESCR>
			</DESCRIPTION>
		</DESCRIPTIONS>
	</GTIP>
	<GTIP>
		<CODE>07.09.60.10.00.14</CODE>
		<LEVEL_>5</LEVEL_>
		<CODEEMPTY>0</CODEEMPTY>
		<SELECTABLE>1</SELECTABLE>
		<DESCRIPTIONS>
			<DESCRIPTION>
				<INDEX_>1</INDEX_>
				<DESCR>Kýrmýzý biber (paprika)</DESCR>
			</DESCRIPTION>
		</DESCRIPTIONS>
	</GTIP>
	<GTIP>
		<CODE>07.09.60.10.00.19</CODE>
		<LEVEL_>5</LEVEL_>
		<CODEEMPTY>0</CODEEMPTY>
		<SELECTABLE>1</SELECTABLE>
		<DESCRIPTIONS>
			<DESCRIPTION>
				<INDEX_>1</INDEX_>
				<DESCR>Diðerleri</DESCR>
			</DESCRIPTION>
		</DESCRIPTIONS>
	</GTIP>
	<GTIP>
		<CODE>07.09.60.10.00.19.0</CODE>
		<LEVEL_>4</LEVEL_>
		<CODEEMPTY>1</CODEEMPTY>
		<SELECTABLE>0</SELECTABLE>
		<DESCRIPTIONS>
			<DESCRIPTION>
				<INDEX_>1</INDEX_>
				<DESCR>Diðerleri:</DESCR>
			</DESCRIPTION>
		</DESCRIPTIONS>
	</GTIP>
	<GTIP>
		<CODE>07.09.60.91.00.00</CODE>
		<LEVEL_>5</LEVEL_>
		<CODEEMPTY>0</CODEEMPTY>
		<SELECTABLE>1</SELECTABLE>
		<DESCRIPTIONS>
			<DESCRIPTION>
				<INDEX_>1</INDEX_>
				<DESCR>Capsicum oleoresin boyalarý ve Capsisin imalinde kullanýlan Capsicum cinsi biberler</DESCR>
			</DESCRIPTION>
		</DESCRIPTIONS>
	</GTIP>
	<GTIP>
		<CODE>07.09.60.95.00.00</CODE>
		<LEVEL_>5</LEVEL_>
		<CODEEMPTY>0</CODEEMPTY>
		<SELECTABLE>1</SELECTABLE>
		<DESCRIPTIONS>
			<DESCRIPTION>
				<INDEX_>1</INDEX_>
				<DESCR>Rezinoit veya uçucu yaðlarýn imalinde kullanýlanlar</DESCR>
			</DESCRIPTION>
		</DESCRIPTIONS>
	</GTIP>
	<GTIP>
		<CODE>07.09.60.99.00.00</CODE>
		<LEVEL_>5</LEVEL_>
		<CODEEMPTY>0</CODEEMPTY>
		<SELECTABLE>1</SELECTABLE>
		<DESCRIPTIONS>
			<DESCRIPTION>
				<INDEX_>1</INDEX_>
				<DESCR>Diðerleri</DESCR>
			</DESCRIPTION>
		</DESCRIPTIONS>
	</GTIP>
	<GTIP>
		<CODE>07.09.70</CODE>
		<LEVEL_>3</LEVEL_>
		<CODEEMPTY>0</CODEEMPTY>
		<SELECTABLE>0</SELECTABLE>
		<DESCRIPTIONS>
			<DESCRIPTION>
				<INDEX_>1</INDEX_>
				<DESCR>Ispanak,Yeni Zelanda ýspanaðý ve bahçe ýspanaðý</DESCR>
			</DESCRIPTION>
		</DESCRIPTIONS>
	</GTIP>
	<GTIP>
		<CODE>07.09.70.00.00.11</CODE>
		<LEVEL_>4</LEVEL_>
		<CODEEMPTY>0</CODEEMPTY>
		<SELECTABLE>1</SELECTABLE>
		<DESCRIPTIONS>
			<DESCRIPTION>
				<INDEX_>1</INDEX_>
				<DESCR>Ispanak</DESCR>
			</DESCRIPTION>
		</DESCRIPTIONS>
	</GTIP>
	<GTIP>
		<CODE>07.09.70.00.00.12</CODE>
		<LEVEL_>4</LEVEL_>
		<CODEEMPTY>0</CODEEMPTY>
		<SELECTABLE>1</SELECTABLE>
		<DESCRIPTIONS>
			<DESCRIPTION>
				<INDEX_>1</INDEX_>
				<DESCR>Yeni Zelanda ýspanaðý</DESCR>
			</DESCRIPTION>
		</DESCRIPTIONS>
	</GTIP>
	<GTIP>
		<CODE>07.09.70.00.00.13</CODE>
		<LEVEL_>4</LEVEL_>
		<CODEEMPTY>0</CODEEMPTY>
		<SELECTABLE>1</SELECTABLE>
		<DESCRIPTIONS>
			<DESCRIPTION>
				<INDEX_>1</INDEX_>
				<DESCR>Bahçe ýspanaðý ( kara pazý )</DESCR>
			</DESCRIPTION>
		</DESCRIPTIONS>
	</GTIP>
	<GTIP>
		<CODE>07.09.90</CODE>
		<LEVEL_>3</LEVEL_>
		<CODEEMPTY>0</CODEEMPTY>
		<SELECTABLE>0</SELECTABLE>
		<DESCRIPTIONS>
			<DESCRIPTION>
				<INDEX_>1</INDEX_>
				<DESCR>Diðerleri:</DESCR>
			</DESCRIPTION>
		</DESCRIPTIONS>
	</GTIP>
	<GTIP>
		<CODE>07.09.90.10.00.00</CODE>
		<LEVEL_>4</LEVEL_>
		<CODEEMPTY>0</CODEEMPTY>
		<SELECTABLE>1</SELECTABLE>
		<DESCRIPTIONS>
			<DESCRIPTION>
				<INDEX_>1</INDEX_>
				<DESCR>Salatalýk sebzeler, (marul (Lactuca sativa) ve hindiba (Cichorium spp.) hariç)</DESCR>
			</DESCRIPTION>
		</DESCRIPTIONS>
	</GTIP>
	<GTIP>
		<CODE>07.09.90.20.00.00</CODE>
		<LEVEL_>4</LEVEL_>
		<CODEEMPTY>0</CODEEMPTY>
		<SELECTABLE>1</SELECTABLE>
		<DESCRIPTIONS>
			<DESCRIPTION>
				<INDEX_>1</INDEX_>
				<DESCR>Pazý ve yaban enginarý</DESCR>
			</DESCRIPTION>
		</DESCRIPTIONS>
	</GTIP>
	<GTIP>
		<CODE>07.09.90.20.00.00.0</CODE>
		<LEVEL_>4</LEVEL_>
		<CODEEMPTY>1</CODEEMPTY>
		<SELECTABLE>0</SELECTABLE>
		<DESCRIPTIONS>
			<DESCRIPTION>
				<INDEX_>1</INDEX_>
				<DESCR>Zeytinler:</DESCR>
			</DESCRIPTION>
		</DESCRIPTIONS>
	</GTIP>
	<GTIP>
		<CODE>07.09.90.31.00.00</CODE>
		<LEVEL_>5</LEVEL_>
		<CODEEMPTY>0</CODEEMPTY>
		<SELECTABLE>1</SELECTABLE>
		<DESCRIPTIONS>
			<DESCRIPTION>
				<INDEX_>1</INDEX_>
				<DESCR>Zeytinyaðý imalinde kullanýlmayanlar</DESCR>
			</DESCRIPTION>
		</DESCRIPTIONS>
	</GTIP>
	<GTIP>
		<CODE>07.09.90.39.00.00</CODE>
		<LEVEL_>5</LEVEL_>
		<CODEEMPTY>0</CODEEMPTY>
		<SELECTABLE>1</SELECTABLE>
		<DESCRIPTIONS>
			<DESCRIPTION>
				<INDEX_>1</INDEX_>
				<DESCR>Diðerleri</DESCR>
			</DESCRIPTION>
		</DESCRIPTIONS>
	</GTIP>
	<GTIP>
		<CODE>07.09.90.40.00.00</CODE>
		<LEVEL_>4</LEVEL_>
		<CODEEMPTY>0</CODEEMPTY>
		<SELECTABLE>1</SELECTABLE>
		<DESCRIPTIONS>
			<DESCRIPTION>
				<INDEX_>1</INDEX_>
				<DESCR>Kebere</DESCR>
			</DESCRIPTION>
		</DESCRIPTIONS>
	</GTIP>
	<GTIP>
		<CODE>07.09.90.50.00.00</CODE>
		<LEVEL_>4</LEVEL_>
		<CODEEMPTY>0</CODEEMPTY>
		<SELECTABLE>1</SELECTABLE>
		<DESCRIPTIONS>
			<DESCRIPTION>
				<INDEX_>1</INDEX_>
				<DESCR>Rezene</DESCR>
			</DESCRIPTION>
		</DESCRIPTIONS>
	</GTIP>
	<GTIP>
		<CODE>07.09.90.60.00.00</CODE>
		<LEVEL_>4</LEVEL_>
		<CODEEMPTY>0</CODEEMPTY>
		<SELECTABLE>1</SELECTABLE>
		<DESCRIPTIONS>
			<DESCRIPTION>
				<INDEX_>1</INDEX_>
				<DESCR>Tatlý mýsýr</DESCR>
			</DESCRIPTION>
		</DESCRIPTIONS>
	</GTIP>
	<GTIP>
		<CODE>07.09.90.60.00.00.0</CODE>
		<LEVEL_>4</LEVEL_>
		<CODEEMPTY>1</CODEEMPTY>
		<SELECTABLE>0</SELECTABLE>
		<DESCRIPTIONS>
			<DESCRIPTION>
				<INDEX_>1</INDEX_>
				<DESCR>Kabaklar</DESCR>
			</DESCRIPTION>
		</DESCRIPTIONS>
	</GTIP>
	<GTIP>
		<CODE>07.09.90.70.00.11</CODE>
		<LEVEL_>5</LEVEL_>
		<CODEEMPTY>0</CODEEMPTY>
		<SELECTABLE>1</SELECTABLE>
		<DESCRIPTIONS>
			<DESCRIPTION>
				<INDEX_>1</INDEX_>
				<DESCR>Dolmalýk kabak</DESCR>
			</DESCRIPTION>
		</DESCRIPTIONS>
	</GTIP>
	<GTIP>
		<CODE>07.09.90.70.00.12</CODE>
		<LEVEL_>5</LEVEL_>
		<CODEEMPTY>0</CODEEMPTY>
		<SELECTABLE>1</SELECTABLE>
		<DESCRIPTIONS>
			<DESCRIPTION>
				<INDEX_>1</INDEX_>
				<DESCR>Bal kabaðý</DESCR>
			</DESCRIPTION>
		</DESCRIPTIONS>
	</GTIP>
	<GTIP>
		<CODE>07.09.90.70.00.13</CODE>
		<LEVEL_>5</LEVEL_>
		<CODEEMPTY>0</CODEEMPTY>
		<SELECTABLE>1</SELECTABLE>
		<DESCRIPTIONS>
			<DESCRIPTION>
				<INDEX_>1</INDEX_>
				<DESCR>Su kabaðý</DESCR>
			</DESCRIPTION>
		</DESCRIPTIONS>
	</GTIP>
	<GTIP>
		<CODE>07.09.90.70.00.14</CODE>
		<LEVEL_>5</LEVEL_>
		<CODEEMPTY>0</CODEEMPTY>
		<SELECTABLE>1</SELECTABLE>
		<DESCRIPTIONS>
			<DESCRIPTION>
				<INDEX_>1</INDEX_>
				<DESCR>Sakýz kabaðý</DESCR>
			</DESCRIPTION>
		</DESCRIPTIONS>
	</GTIP>
	<GTIP>
		<CODE>07.09.90.70.00.19</CODE>
		<LEVEL_>5</LEVEL_>
		<CODEEMPTY>0</CODEEMPTY>
		<SELECTABLE>1</SELECTABLE>
		<DESCRIPTIONS>
			<DESCRIPTION>
				<INDEX_>1</INDEX_>
				<DESCR>Diðerleri</DESCR>
			</DESCRIPTION>
		</DESCRIPTIONS>
	</GTIP>
	<GTIP>
		<CODE>07.09.90.80.00.00</CODE>
		<LEVEL_>4</LEVEL_>
		<CODEEMPTY>0</CODEEMPTY>
		<SELECTABLE>1</SELECTABLE>
		<DESCRIPTIONS>
			<DESCRIPTION>
				<INDEX_>1</INDEX_>
				<DESCR>Enginarlar</DESCR>
			</DESCRIPTION>
		</DESCRIPTIONS>
	</GTIP>
	<GTIP>
		<CODE>07.09.90.80.00.00.0</CODE>
		<LEVEL_>4</LEVEL_>
		<CODEEMPTY>1</CODEEMPTY>
		<SELECTABLE>0</SELECTABLE>
		<DESCRIPTIONS>
			<DESCRIPTION>
				<INDEX_>1</INDEX_>
				<DESCR>Diðerleri</DESCR>
			</DESCRIPTION>
		</DESCRIPTIONS>
	</GTIP>
	<GTIP>
		<CODE>07.09.90.90.00.11</CODE>
		<LEVEL_>5</LEVEL_>
		<CODEEMPTY>0</CODEEMPTY>
		<SELECTABLE>1</SELECTABLE>
		<DESCRIPTIONS>
			<DESCRIPTION>
				<INDEX_>1</INDEX_>
				<DESCR>Bamya</DESCR>
			</DESCRIPTION>
		</DESCRIPTIONS>
	</GTIP>
	<GTIP>
		<CODE>07.09.90.90.00.12</CODE>
		<LEVEL_>5</LEVEL_>
		<CODEEMPTY>0</CODEEMPTY>
		<SELECTABLE>1</SELECTABLE>
		<DESCRIPTIONS>
			<DESCRIPTION>
				<INDEX_>1</INDEX_>
				<DESCR>Semizotu</DESCR>
			</DESCRIPTION>
		</DESCRIPTIONS>
	</GTIP>
	<GTIP>
		<CODE>07.09.90.90.00.13</CODE>
		<LEVEL_>5</LEVEL_>
		<CODEEMPTY>0</CODEEMPTY>
		<SELECTABLE>1</SELECTABLE>
		<DESCRIPTIONS>
			<DESCRIPTION>
				<INDEX_>1</INDEX_>
				<DESCR>Maydanoz</DESCR>
			</DESCRIPTION>
		</DESCRIPTIONS>
	</GTIP>
	<GTIP>
		<CODE>07.09.90.90.00.14</CODE>
		<LEVEL_>5</LEVEL_>
		<CODEEMPTY>0</CODEEMPTY>
		<SELECTABLE>1</SELECTABLE>
		<DESCRIPTIONS>
			<DESCRIPTION>
				<INDEX_>1</INDEX_>
				<DESCR>Asma yapraðý</DESCR>
			</DESCRIPTION>
		</DESCRIPTIONS>
	</GTIP>
	<GTIP>
		<CODE>07.09.90.90.00.18</CODE>
		<LEVEL_>5</LEVEL_>
		<CODEEMPTY>0</CODEEMPTY>
		<SELECTABLE>1</SELECTABLE>
		<DESCRIPTIONS>
			<DESCRIPTION>
				<INDEX_>1</INDEX_>
				<DESCR>Diðerleri</DESCR>
			</DESCRIPTION>
		</DESCRIPTIONS>
	</GTIP>
	<GTIP>
		<CODE>07.10</CODE>
		<LEVEL_>2</LEVEL_>
		<CODEEMPTY>0</CODEEMPTY>
		<SELECTABLE>0</SELECTABLE>
		<DESCRIPTIONS>
			<DESCRIPTION>
				<INDEX_>1</INDEX_>
				<DESCR>Sebzeler (piþirilmemiþ veya buharda veya suda kaynatýlarak piþirilmiþ) (dondurulmuþ):</DESCR>
			</DESCRIPTION>
		</DESCRIPTIONS>
	</GTIP>
	<GTIP>
		<CODE>07.10.10.00.00.00</CODE>
		<LEVEL_>3</LEVEL_>
		<CODEEMPTY>0</CODEEMPTY>
		<SELECTABLE>1</SELECTABLE>
		<DESCRIPTIONS>
			<DESCRIPTION>
				<INDEX_>1</INDEX_>
				<DESCR>Patates</DESCR>
			</DESCRIPTION>
		</DESCRIPTIONS>
	</GTIP>
	<GTIP>
		<CODE>07.10.10.00.00.00.0</CODE>
		<LEVEL_>3</LEVEL_>
		<CODEEMPTY>1</CODEEMPTY>
		<SELECTABLE>0</SELECTABLE>
		<DESCRIPTIONS>
			<DESCRIPTION>
				<INDEX_>1</INDEX_>
				<DESCR>Baklagil sebzeler (kabuklu veya kabuksuz):</DESCR>
			</DESCRIPTION>
		</DESCRIPTIONS>
	</GTIP>
	<GTIP>
		<CODE>07.10.21.00.00.00</CODE>
		<LEVEL_>4</LEVEL_>
		<CODEEMPTY>0</CODEEMPTY>
		<SELECTABLE>1</SELECTABLE>
		<DESCRIPTIONS>
			<DESCRIPTION>
				<INDEX_>1</INDEX_>
				<DESCR>Bezelye (Pisum sativum)</DESCR>
			</DESCRIPTION>
		</DESCRIPTIONS>
	</GTIP>
	<GTIP>
		<CODE>07.10.22.00.00.00</CODE>
		<LEVEL_>4</LEVEL_>
		<CODEEMPTY>0</CODEEMPTY>
		<SELECTABLE>1</SELECTABLE>
		<DESCRIPTIONS>
			<DESCRIPTION>
				<INDEX_>1</INDEX_>
				<DESCR>Fasulye (Phaseolus spp., Vigna spp.)</DESCR>
			</DESCRIPTION>
		</DESCRIPTIONS>
	</GTIP>
	<GTIP>
		<CODE>07.10.29.00.00.00</CODE>
		<LEVEL_>4</LEVEL_>
		<CODEEMPTY>0</CODEEMPTY>
		<SELECTABLE>1</SELECTABLE>
		<DESCRIPTIONS>
			<DESCRIPTION>
				<INDEX_>1</INDEX_>
				<DESCR>Diðerleri</DESCR>
			</DESCRIPTION>
		</DESCRIPTIONS>
	</GTIP>
	<GTIP>
		<CODE>07.10.30.00.00.00</CODE>
		<LEVEL_>3</LEVEL_>
		<CODEEMPTY>0</CODEEMPTY>
		<SELECTABLE>1</SELECTABLE>
		<DESCRIPTIONS>
			<DESCRIPTION>
				<INDEX_>1</INDEX_>
				<DESCR>Ispanak, Yeni Zelanda ýspanaðý ve bahçe ýspanaðý</DESCR>
			</DESCRIPTION>
		</DESCRIPTIONS>
	</GTIP>
	<GTIP>
		<CODE>07.10.40.00.00.00</CODE>
		<LEVEL_>3</LEVEL_>
		<CODEEMPTY>0</CODEEMPTY>
		<SELECTABLE>1</SELECTABLE>
		<DESCRIPTIONS>
			<DESCRIPTION>
				<INDEX_>1</INDEX_>
				<DESCR>Tatlý mýsýr</DESCR>
			</DESCRIPTION>
		</DESCRIPTIONS>
	</GTIP>
	<GTIP>
		<CODE>07.10.80</CODE>
		<LEVEL_>3</LEVEL_>
		<CODEEMPTY>0</CODEEMPTY>
		<SELECTABLE>0</SELECTABLE>
		<DESCRIPTIONS>
			<DESCRIPTION>
				<INDEX_>1</INDEX_>
				<DESCR>Diðer sebzeler:</DESCR>
			</DESCRIPTION>
		</DESCRIPTIONS>
	</GTIP>
	<GTIP>
		<CODE>07.10.80.10.00.00</CODE>
		<LEVEL_>4</LEVEL_>
		<CODEEMPTY>0</CODEEMPTY>
		<SELECTABLE>1</SELECTABLE>
		<DESCRIPTIONS>
			<DESCRIPTION>
				<INDEX_>1</INDEX_>
				<DESCR>Zeytinler</DESCR>
			</DESCRIPTION>
		</DESCRIPTIONS>
	</GTIP>
	<GTIP>
		<CODE>07.10.80.10.00.00.0</CODE>
		<LEVEL_>4</LEVEL_>
		<CODEEMPTY>1</CODEEMPTY>
		<SELECTABLE>0</SELECTABLE>
		<DESCRIPTIONS>
			<DESCRIPTION>
				<INDEX_>1</INDEX_>
				<DESCR>Capsicum veya Pimenta cinsi meyvalar :</DESCR>
			</DESCRIPTION>
		</DESCRIPTIONS>
	</GTIP>
	<GTIP>
		<CODE>07.10.80.51.00.00</CODE>
		<LEVEL_>5</LEVEL_>
		<CODEEMPTY>0</CODEEMPTY>
		<SELECTABLE>1</SELECTABLE>
		<DESCRIPTIONS>
			<DESCRIPTION>
				<INDEX_>1</INDEX_>
				<DESCR>Tatlý biberler</DESCR>
			</DESCRIPTION>
		</DESCRIPTIONS>
	</GTIP>
	<GTIP>
		<CODE>07.10.80.59.00.00</CODE>
		<LEVEL_>5</LEVEL_>
		<CODEEMPTY>0</CODEEMPTY>
		<SELECTABLE>1</SELECTABLE>
		<DESCRIPTIONS>
			<DESCRIPTION>
				<INDEX_>1</INDEX_>
				<DESCR>Diðerleri</DESCR>
			</DESCRIPTION>
		</DESCRIPTIONS>
	</GTIP>
	<GTIP>
		<CODE>07.10.80.59.00.00.0</CODE>
		<LEVEL_>4</LEVEL_>
		<CODEEMPTY>1</CODEEMPTY>
		<SELECTABLE>0</SELECTABLE>
		<DESCRIPTIONS>
			<DESCRIPTION>
				<INDEX_>1</INDEX_>
				<DESCR>Mantarlar</DESCR>
			</DESCRIPTION>
		</DESCRIPTIONS>
	</GTIP>
	<GTIP>
		<CODE>07.10.80.61.00.00</CODE>
		<LEVEL_>5</LEVEL_>
		<CODEEMPTY>0</CODEEMPTY>
		<SELECTABLE>1</SELECTABLE>
		<DESCRIPTIONS>
			<DESCRIPTION>
				<INDEX_>1</INDEX_>
				<DESCR>Agaricus cinsi mantarlar</DESCR>
			</DESCRIPTION>
		</DESCRIPTIONS>
	</GTIP>
	<GTIP>
		<CODE>07.10.80.69.00.00</CODE>
		<LEVEL_>5</LEVEL_>
		<CODEEMPTY>0</CODEEMPTY>
		<SELECTABLE>1</SELECTABLE>
		<DESCRIPTIONS>
			<DESCRIPTION>
				<INDEX_>1</INDEX_>
				<DESCR>Diðerleri</DESCR>
			</DESCRIPTION>
		</DESCRIPTIONS>
	</GTIP>
	<GTIP>
		<CODE>07.10.80.70.00.00</CODE>
		<LEVEL_>4</LEVEL_>
		<CODEEMPTY>0</CODEEMPTY>
		<SELECTABLE>1</SELECTABLE>
		<DESCRIPTIONS>
			<DESCRIPTION>
				<INDEX_>1</INDEX_>
				<DESCR>Domatesler</DESCR>
			</DESCRIPTION>
		</DESCRIPTIONS>
	</GTIP>
	<GTIP>
		<CODE>07.10.80.80.00.00</CODE>
		<LEVEL_>4</LEVEL_>
		<CODEEMPTY>0</CODEEMPTY>
		<SELECTABLE>1</SELECTABLE>
		<DESCRIPTIONS>
			<DESCRIPTION>
				<INDEX_>1</INDEX_>
				<DESCR>Enginarlar</DESCR>
			</DESCRIPTION>
		</DESCRIPTIONS>
	</GTIP>
	<GTIP>
		<CODE>07.10.80.85.00.00</CODE>
		<LEVEL_>4</LEVEL_>
		<CODEEMPTY>0</CODEEMPTY>
		<SELECTABLE>1</SELECTABLE>
		<DESCRIPTIONS>
			<DESCRIPTION>
				<INDEX_>1</INDEX_>
				<DESCR>Kuþkonmazlar</DESCR>
			</DESCRIPTION>
		</DESCRIPTIONS>
	</GTIP>
	<GTIP>
		<CODE>07.10.80.85.00.00.0</CODE>
		<LEVEL_>4</LEVEL_>
		<CODEEMPTY>1</CODEEMPTY>
		<SELECTABLE>0</SELECTABLE>
		<DESCRIPTIONS>
			<DESCRIPTION>
				<INDEX_>1</INDEX_>
				<DESCR>Diðerleri</DESCR>
			</DESCRIPTION>
		</DESCRIPTIONS>
	</GTIP>
	<GTIP>
		<CODE>07.10.80.95.00.11</CODE>
		<LEVEL_>5</LEVEL_>
		<CODEEMPTY>0</CODEEMPTY>
		<SELECTABLE>1</SELECTABLE>
		<DESCRIPTIONS>
			<DESCRIPTION>
				<INDEX_>1</INDEX_>
				<DESCR>Soðan</DESCR>
			</DESCRIPTION>
		</DESCRIPTIONS>
	</GTIP>
	<GTIP>
		<CODE>07.10.80.95.00.12</CODE>
		<LEVEL_>5</LEVEL_>
		<CODEEMPTY>0</CODEEMPTY>
		<SELECTABLE>1</SELECTABLE>
		<DESCRIPTIONS>
			<DESCRIPTION>
				<INDEX_>1</INDEX_>
				<DESCR>Havuç</DESCR>
			</DESCRIPTION>
		</DESCRIPTIONS>
	</GTIP>
	<GTIP>
		<CODE>07.10.80.95.00.13</CODE>
		<LEVEL_>5</LEVEL_>
		<CODEEMPTY>0</CODEEMPTY>
		<SELECTABLE>1</SELECTABLE>
		<DESCRIPTIONS>
			<DESCRIPTION>
				<INDEX_>1</INDEX_>
				<DESCR>Pýrasa</DESCR>
			</DESCRIPTION>
		</DESCRIPTIONS>
	</GTIP>
	<GTIP>
		<CODE>07.10.80.95.00.14</CODE>
		<LEVEL_>5</LEVEL_>
		<CODEEMPTY>0</CODEEMPTY>
		<SELECTABLE>1</SELECTABLE>
		<DESCRIPTIONS>
			<DESCRIPTION>
				<INDEX_>1</INDEX_>
				<DESCR>Karnabahar</DESCR>
			</DESCRIPTION>
		</DESCRIPTIONS>
	</GTIP>
	<GTIP>
		<CODE>07.10.80.95.00.15</CODE>
		<LEVEL_>5</LEVEL_>
		<CODEEMPTY>0</CODEEMPTY>
		<SELECTABLE>1</SELECTABLE>
		<DESCRIPTIONS>
			<DESCRIPTION>
				<INDEX_>1</INDEX_>
				<DESCR>Lahana</DESCR>
			</DESCRIPTION>
		</DESCRIPTIONS>
	</GTIP>
	<GTIP>
		<CODE>07.10.80.95.00.19</CODE>
		<LEVEL_>5</LEVEL_>
		<CODEEMPTY>0</CODEEMPTY>
		<SELECTABLE>1</SELECTABLE>
		<DESCRIPTIONS>
			<DESCRIPTION>
				<INDEX_>1</INDEX_>
				<DESCR>Diðerleri</DESCR>
			</DESCRIPTION>
		</DESCRIPTIONS>
	</GTIP>
	<GTIP>
		<CODE>07.10.90.00.00.00</CODE>
		<LEVEL_>3</LEVEL_>
		<CODEEMPTY>0</CODEEMPTY>
		<SELECTABLE>1</SELECTABLE>
		<DESCRIPTIONS>
			<DESCRIPTION>
				<INDEX_>1</INDEX_>
				<DESCR>Sebze karýþýmlarý</DESCR>
			</DESCRIPTION>
		</DESCRIPTIONS>
	</GTIP>
	<GTIP>
		<CODE>07.11</CODE>
		<LEVEL_>2</LEVEL_>
		<CODEEMPTY>0</CODEEMPTY>
		<SELECTABLE>0</SELECTABLE>
		<DESCRIPTIONS>
			<DESCRIPTION>
				<INDEX_>1</INDEX_>
				<DESCR>Geçici olarak konserve edilmiþ (örneðin; kükürtdioksit gazý kullanýlarak salamurada, kükürtlü su içinde veya diðer koruyucu eriyikler içinde); fakat b</DESCR>
			</DESCRIPTION>
			<DESCRIPTION>
				<INDEX_>2</INDEX_>
				<DESCR>u halleriyle derhal yenilmeye elveriþli olmayan sebzeler:</DESCR>
			</DESCRIPTION>
		</DESCRIPTIONS>
	</GTIP>
	<GTIP>
		<CODE>07.11.20</CODE>
		<LEVEL_>3</LEVEL_>
		<CODEEMPTY>0</CODEEMPTY>
		<SELECTABLE>0</SELECTABLE>
		<DESCRIPTIONS>
			<DESCRIPTION>
				<INDEX_>1</INDEX_>
				<DESCR>Zeytinler :</DESCR>
			</DESCRIPTION>
		</DESCRIPTIONS>
	</GTIP>
	<GTIP>
		<CODE>07.11.20.10.00.00</CODE>
		<LEVEL_>4</LEVEL_>
		<CODEEMPTY>0</CODEEMPTY>
		<SELECTABLE>1</SELECTABLE>
		<DESCRIPTIONS>
			<DESCRIPTION>
				<INDEX_>1</INDEX_>
				<DESCR>Zeytinyaðý imalinde kullanýlmayanlar</DESCR>
			</DESCRIPTION>
		</DESCRIPTIONS>
	</GTIP>
	<GTIP>
		<CODE>07.11.20.90.00.00</CODE>
		<LEVEL_>4</LEVEL_>
		<CODEEMPTY>0</CODEEMPTY>
		<SELECTABLE>1</SELECTABLE>
		<DESCRIPTIONS>
			<DESCRIPTION>
				<INDEX_>1</INDEX_>
				<DESCR>Diðerleri</DESCR>
			</DESCRIPTION>
		</DESCRIPTIONS>
	</GTIP>
	<GTIP>
		<CODE>07.11.40.00.00.00</CODE>
		<LEVEL_>3</LEVEL_>
		<CODEEMPTY>0</CODEEMPTY>
		<SELECTABLE>1</SELECTABLE>
		<DESCRIPTIONS>
			<DESCRIPTION>
				<INDEX_>1</INDEX_>
				<DESCR>Hýyarlar ve korniþonlar</DESCR>
			</DESCRIPTION>
		</DESCRIPTIONS>
	</GTIP>
	<GTIP>
		<CODE>07.11.40.00.00.00.0</CODE>
		<LEVEL_>3</LEVEL_>
		<CODEEMPTY>1</CODEEMPTY>
		<SELECTABLE>0</SELECTABLE>
		<DESCRIPTIONS>
			<DESCRIPTION>
				<INDEX_>1</INDEX_>
				<DESCR>Mantarlar ve domalanlar:</DESCR>
			</DESCRIPTION>
		</DESCRIPTIONS>
	</GTIP>
	<GTIP>
		<CODE>07.11.51.00.00.00</CODE>
		<LEVEL_>4</LEVEL_>
		<CODEEMPTY>0</CODEEMPTY>
		<SELECTABLE>1</SELECTABLE>
		<DESCRIPTIONS>
			<DESCRIPTION>
				<INDEX_>1</INDEX_>
				<DESCR>Agaricus cinsi mantarlar</DESCR>
			</DESCRIPTION>
		</DESCRIPTIONS>
	</GTIP>
	<GTIP>
		<CODE>07.11.59.00.00.00</CODE>
		<LEVEL_>4</LEVEL_>
		<CODEEMPTY>0</CODEEMPTY>
		<SELECTABLE>1</SELECTABLE>
		<DESCRIPTIONS>
			<DESCRIPTION>
				<INDEX_>1</INDEX_>
				<DESCR>Diðerleri</DESCR>
			</DESCRIPTION>
		</DESCRIPTIONS>
	</GTIP>
	<GTIP>
		<CODE>07.11.90</CODE>
		<LEVEL_>3</LEVEL_>
		<CODEEMPTY>0</CODEEMPTY>
		<SELECTABLE>0</SELECTABLE>
		<DESCRIPTIONS>
			<DESCRIPTION>
				<INDEX_>1</INDEX_>
				<DESCR>Diðer sebzeler; sebze karýþýmlarý:</DESCR>
			</DESCRIPTION>
		</DESCRIPTIONS>
	</GTIP>
	<GTIP>
		<CODE>07.11.90.0</CODE>
		<LEVEL_>4</LEVEL_>
		<CODEEMPTY>1</CODEEMPTY>
		<SELECTABLE>0</SELECTABLE>
		<DESCRIPTIONS>
			<DESCRIPTION>
				<INDEX_>1</INDEX_>
				<DESCR>Sebzeler:</DESCR>
			</DESCRIPTION>
		</DESCRIPTIONS>
	</GTIP>
	<GTIP>
		<CODE>07.11.90.10.00.00</CODE>
		<LEVEL_>5</LEVEL_>
		<CODEEMPTY>0</CODEEMPTY>
		<SELECTABLE>1</SELECTABLE>
		<DESCRIPTIONS>
			<DESCRIPTION>
				<INDEX_>1</INDEX_>
				<DESCR>Capsicum ve Pimenta cinsi meyvalar (tatlý biberler hariç)</DESCR>
			</DESCRIPTION>
		</DESCRIPTIONS>
	</GTIP>
	<GTIP>
		<CODE>07.11.90.30.00.00</CODE>
		<LEVEL_>5</LEVEL_>
		<CODEEMPTY>0</CODEEMPTY>
		<SELECTABLE>1</SELECTABLE>
		<DESCRIPTIONS>
			<DESCRIPTION>
				<INDEX_>1</INDEX_>
				<DESCR>Tatlý mýsýr</DESCR>
			</DESCRIPTION>
		</DESCRIPTIONS>
	</GTIP>
	<GTIP>
		<CODE>07.11.90.50.00.00</CODE>
		<LEVEL_>5</LEVEL_>
		<CODEEMPTY>0</CODEEMPTY>
		<SELECTABLE>1</SELECTABLE>
		<DESCRIPTIONS>
			<DESCRIPTION>
				<INDEX_>1</INDEX_>
				<DESCR>Soðanlar</DESCR>
			</DESCRIPTION>
		</DESCRIPTIONS>
	</GTIP>
	<GTIP>
		<CODE>07.11.90.70.00.00</CODE>
		<LEVEL_>5</LEVEL_>
		<CODEEMPTY>0</CODEEMPTY>
		<SELECTABLE>1</SELECTABLE>
		<DESCRIPTIONS>
			<DESCRIPTION>
				<INDEX_>1</INDEX_>
				<DESCR>Kebere</DESCR>
			</DESCRIPTION>
		</DESCRIPTIONS>
	</GTIP>
	<GTIP>
		<CODE>07.11.90.80.00.00</CODE>
		<LEVEL_>5</LEVEL_>
		<CODEEMPTY>0</CODEEMPTY>
		<SELECTABLE>1</SELECTABLE>
		<DESCRIPTIONS>
			<DESCRIPTION>
				<INDEX_>1</INDEX_>
				<DESCR>Diðerleri</DESCR>
			</DESCRIPTION>
		</DESCRIPTIONS>
	</GTIP>
	<GTIP>
		<CODE>07.11.90.90.00.00</CODE>
		<LEVEL_>4</LEVEL_>
		<CODEEMPTY>0</CODEEMPTY>
		<SELECTABLE>1</SELECTABLE>
		<DESCRIPTIONS>
			<DESCRIPTION>
				<INDEX_>1</INDEX_>
				<DESCR>Sebze karýþýmlarý</DESCR>
			</DESCRIPTION>
		</DESCRIPTIONS>
	</GTIP>
	<GTIP>
		<CODE>07.12</CODE>
		<LEVEL_>2</LEVEL_>
		<CODEEMPTY>0</CODEEMPTY>
		<SELECTABLE>0</SELECTABLE>
		<DESCRIPTIONS>
			<DESCRIPTION>
				<INDEX_>1</INDEX_>
				<DESCR>Kurutulmuþ sebzeler (bütün halde, kesilmiþ, dilimlenmiþ ,kýrýlmýþ veya toz halinde, fakat baþka þekilde hazýrlanmamýþ):</DESCR>
			</DESCRIPTION>
		</DESCRIPTIONS>
	</GTIP>
	<GTIP>
		<CODE>07.12.20.00.00.00</CODE>
		<LEVEL_>3</LEVEL_>
		<CODEEMPTY>0</CODEEMPTY>
		<SELECTABLE>1</SELECTABLE>
		<DESCRIPTIONS>
			<DESCRIPTION>
				<INDEX_>1</INDEX_>
				<DESCR>Soðanlar</DESCR>
			</DESCRIPTION>
		</DESCRIPTIONS>
	</GTIP>
	<GTIP>
		<CODE>07.12.20.00.00.00.0</CODE>
		<LEVEL_>3</LEVEL_>
		<CODEEMPTY>1</CODEEMPTY>
		<SELECTABLE>0</SELECTABLE>
		<DESCRIPTIONS>
			<DESCRIPTION>
				<INDEX_>1</INDEX_>
				<DESCR>Mantarlar, yahudi kulaðý (Auricularia spp.), jöle mantarý (Tremella spp.) ve domalanlar:</DESCR>
			</DESCRIPTION>
		</DESCRIPTIONS>
	</GTIP>
	<GTIP>
		<CODE>07.12.31.00.00.00</CODE>
		<LEVEL_>4</LEVEL_>
		<CODEEMPTY>0</CODEEMPTY>
		<SELECTABLE>1</SELECTABLE>
		<DESCRIPTIONS>
			<DESCRIPTION>
				<INDEX_>1</INDEX_>
				<DESCR>Agaricus cinsi mantarlar</DESCR>
			</DESCRIPTION>
		</DESCRIPTIONS>
	</GTIP>
	<GTIP>
		<CODE>07.12.32.00.00.00</CODE>
		<LEVEL_>4</LEVEL_>
		<CODEEMPTY>0</CODEEMPTY>
		<SELECTABLE>1</SELECTABLE>
		<DESCRIPTIONS>
			<DESCRIPTION>
				<INDEX_>1</INDEX_>
				<DESCR>Yahudi kulaðý (Auricularia spp.)</DESCR>
			</DESCRIPTION>
		</DESCRIPTIONS>
	</GTIP>
	<GTIP>
		<CODE>07.12.33.00.00.00</CODE>
		<LEVEL_>4</LEVEL_>
		<CODEEMPTY>0</CODEEMPTY>
		<SELECTABLE>1</SELECTABLE>
		<DESCRIPTIONS>
			<DESCRIPTION>
				<INDEX_>1</INDEX_>
				<DESCR>Jöle mantarý (Tremella spp.)</DESCR>
			</DESCRIPTION>
		</DESCRIPTIONS>
	</GTIP>
	<GTIP>
		<CODE>07.12.39.00.00.00</CODE>
		<LEVEL_>4</LEVEL_>
		<CODEEMPTY>0</CODEEMPTY>
		<SELECTABLE>1</SELECTABLE>
		<DESCRIPTIONS>
			<DESCRIPTION>
				<INDEX_>1</INDEX_>
				<DESCR>Diðerleri</DESCR>
			</DESCRIPTION>
		</DESCRIPTIONS>
	</GTIP>
	<GTIP>
		<CODE>07.12.90</CODE>
		<LEVEL_>3</LEVEL_>
		<CODEEMPTY>0</CODEEMPTY>
		<SELECTABLE>0</SELECTABLE>
		<DESCRIPTIONS>
			<DESCRIPTION>
				<INDEX_>1</INDEX_>
				<DESCR>Diðer sebzeler; sebze karýþýmlarý :</DESCR>
			</DESCRIPTION>
		</DESCRIPTIONS>
	</GTIP>
	<GTIP>
		<CODE>07.12.90.05.00.00</CODE>
		<LEVEL_>4</LEVEL_>
		<CODEEMPTY>0</CODEEMPTY>
		<SELECTABLE>1</SELECTABLE>
		<DESCRIPTIONS>
			<DESCRIPTION>
				<INDEX_>1</INDEX_>
				<DESCR>Patates (kesilmiþ veya dilimlenmiþ olsun olmasýn, fakat baþka þekilde hazýrlanmamýþ)</DESCR>
			</DESCRIPTION>
		</DESCRIPTIONS>
	</GTIP>
	<GTIP>
		<CODE>07.12.90.05.00.00.0</CODE>
		<LEVEL_>4</LEVEL_>
		<CODEEMPTY>1</CODEEMPTY>
		<SELECTABLE>0</SELECTABLE>
		<DESCRIPTIONS>
			<DESCRIPTION>
				<INDEX_>1</INDEX_>
				<DESCR>Tatlý mýsýr (Zea Mays var. Saccharata):</DESCR>
			</DESCRIPTION>
		</DESCRIPTIONS>
	</GTIP>
	<GTIP>
		<CODE>07.12.90.11.00.00</CODE>
		<LEVEL_>5</LEVEL_>
		<CODEEMPTY>0</CODEEMPTY>
		<SELECTABLE>1</SELECTABLE>
		<DESCRIPTIONS>
			<DESCRIPTION>
				<INDEX_>1</INDEX_>
				<DESCR>Tohumluk (melez)</DESCR>
			</DESCRIPTION>
		</DESCRIPTIONS>
	</GTIP>
	<GTIP>
		<CODE>07.12.90.19.00.00</CODE>
		<LEVEL_>5</LEVEL_>
		<CODEEMPTY>0</CODEEMPTY>
		<SELECTABLE>1</SELECTABLE>
		<DESCRIPTIONS>
			<DESCRIPTION>
				<INDEX_>1</INDEX_>
				<DESCR>Diðerleri</DESCR>
			</DESCRIPTION>
		</DESCRIPTIONS>
	</GTIP>
	<GTIP>
		<CODE>07.12.90.30.00.00</CODE>
		<LEVEL_>4</LEVEL_>
		<CODEEMPTY>0</CODEEMPTY>
		<SELECTABLE>1</SELECTABLE>
		<DESCRIPTIONS>
			<DESCRIPTION>
				<INDEX_>1</INDEX_>
				<DESCR>Domates</DESCR>
			</DESCRIPTION>
		</DESCRIPTIONS>
	</GTIP>
	<GTIP>
		<CODE>07.12.90.50.00.00</CODE>
		<LEVEL_>4</LEVEL_>
		<CODEEMPTY>0</CODEEMPTY>
		<SELECTABLE>1</SELECTABLE>
		<DESCRIPTIONS>
			<DESCRIPTION>
				<INDEX_>1</INDEX_>
				<DESCR>Havuç</DESCR>
			</DESCRIPTION>
		</DESCRIPTIONS>
	</GTIP>
	<GTIP>
		<CODE>07.12.90.50.00.00.0</CODE>
		<LEVEL_>4</LEVEL_>
		<CODEEMPTY>1</CODEEMPTY>
		<SELECTABLE>0</SELECTABLE>
		<DESCRIPTIONS>
			<DESCRIPTION>
				<INDEX_>1</INDEX_>
				<DESCR>Diðerleri</DESCR>
			</DESCRIPTION>
		</DESCRIPTIONS>
	</GTIP>
	<GTIP>
		<CODE>07.12.90.90.00.11</CODE>
		<LEVEL_>5</LEVEL_>
		<CODEEMPTY>0</CODEEMPTY>
		<SELECTABLE>1</SELECTABLE>
		<DESCRIPTIONS>
			<DESCRIPTION>
				<INDEX_>1</INDEX_>
				<DESCR>Sarýmsak</DESCR>
			</DESCRIPTION>
		</DESCRIPTIONS>
	</GTIP>
	<GTIP>
		<CODE>07.12.90.90.00.12</CODE>
		<LEVEL_>5</LEVEL_>
		<CODEEMPTY>0</CODEEMPTY>
		<SELECTABLE>1</SELECTABLE>
		<DESCRIPTIONS>
			<DESCRIPTION>
				<INDEX_>1</INDEX_>
				<DESCR>Pýrasa</DESCR>
			</DESCRIPTION>
		</DESCRIPTIONS>
	</GTIP>
	<GTIP>
		<CODE>07.12.90.90.00.13</CODE>
		<LEVEL_>5</LEVEL_>
		<CODEEMPTY>0</CODEEMPTY>
		<SELECTABLE>1</SELECTABLE>
		<DESCRIPTIONS>
			<DESCRIPTION>
				<INDEX_>1</INDEX_>
				<DESCR>Ispanak</DESCR>
			</DESCRIPTION>
		</DESCRIPTIONS>
	</GTIP>
	<GTIP>
		<CODE>07.12.90.90.00.14</CODE>
		<LEVEL_>5</LEVEL_>
		<CODEEMPTY>0</CODEEMPTY>
		<SELECTABLE>1</SELECTABLE>
		<DESCRIPTIONS>
			<DESCRIPTION>
				<INDEX_>1</INDEX_>
				<DESCR>Kuþkonmaz</DESCR>
			</DESCRIPTION>
		</DESCRIPTIONS>
	</GTIP>
	<GTIP>
		<CODE>07.12.90.90.00.15</CODE>
		<LEVEL_>5</LEVEL_>
		<CODEEMPTY>0</CODEEMPTY>
		<SELECTABLE>1</SELECTABLE>
		<DESCRIPTIONS>
			<DESCRIPTION>
				<INDEX_>1</INDEX_>
				<DESCR>Bamya</DESCR>
			</DESCRIPTION>
		</DESCRIPTIONS>
	</GTIP>
	<GTIP>
		<CODE>07.12.90.90.00.16</CODE>
		<LEVEL_>5</LEVEL_>
		<CODEEMPTY>0</CODEEMPTY>
		<SELECTABLE>1</SELECTABLE>
		<DESCRIPTIONS>
			<DESCRIPTION>
				<INDEX_>1</INDEX_>
				<DESCR>Bezelye</DESCR>
			</DESCRIPTION>
		</DESCRIPTIONS>
	</GTIP>
	<GTIP>
		<CODE>07.12.90.90.00.17</CODE>
		<LEVEL_>5</LEVEL_>
		<CODEEMPTY>0</CODEEMPTY>
		<SELECTABLE>1</SELECTABLE>
		<DESCRIPTIONS>
			<DESCRIPTION>
				<INDEX_>1</INDEX_>
				<DESCR>Kabak</DESCR>
			</DESCRIPTION>
		</DESCRIPTIONS>
	</GTIP>
	<GTIP>
		<CODE>07.12.90.90.00.18</CODE>
		<LEVEL_>5</LEVEL_>
		<CODEEMPTY>0</CODEEMPTY>
		<SELECTABLE>1</SELECTABLE>
		<DESCRIPTIONS>
			<DESCRIPTION>
				<INDEX_>1</INDEX_>
				<DESCR>Karnabahar</DESCR>
			</DESCRIPTION>
		</DESCRIPTIONS>
	</GTIP>
	<GTIP>
		<CODE>07.12.90.90.00.21</CODE>
		<LEVEL_>5</LEVEL_>
		<CODEEMPTY>0</CODEEMPTY>
		<SELECTABLE>1</SELECTABLE>
		<DESCRIPTIONS>
			<DESCRIPTION>
				<INDEX_>1</INDEX_>
				<DESCR>Lahana</DESCR>
			</DESCRIPTION>
		</DESCRIPTIONS>
	</GTIP>
	<GTIP>
		<CODE>07.12.90.90.00.22</CODE>
		<LEVEL_>5</LEVEL_>
		<CODEEMPTY>0</CODEEMPTY>
		<SELECTABLE>1</SELECTABLE>
		<DESCRIPTIONS>
			<DESCRIPTION>
				<INDEX_>1</INDEX_>
				<DESCR>Patlýcan</DESCR>
			</DESCRIPTION>
		</DESCRIPTIONS>
	</GTIP>
	<GTIP>
		<CODE>07.12.90.90.00.29</CODE>
		<LEVEL_>5</LEVEL_>
		<CODEEMPTY>0</CODEEMPTY>
		<SELECTABLE>1</SELECTABLE>
		<DESCRIPTIONS>
			<DESCRIPTION>
				<INDEX_>1</INDEX_>
				<DESCR>Diðerleri</DESCR>
			</DESCRIPTION>
		</DESCRIPTIONS>
	</GTIP>
	<GTIP>
		<CODE>07.13</CODE>
		<LEVEL_>2</LEVEL_>
		<CODEEMPTY>0</CODEEMPTY>
		<SELECTABLE>0</SELECTABLE>
		<DESCRIPTIONS>
			<DESCRIPTION>
				<INDEX_>1</INDEX_>
				<DESCR>Kuru baklagiller (kabuksuz) (taneleri ikiye ayrýlmýþ,tane kabuklarý çýkarýlmýþ olsun olmasýn):</DESCR>
			</DESCRIPTION>
		</DESCRIPTIONS>
	</GTIP>
	<GTIP>
		<CODE>07.13.10</CODE>
		<LEVEL_>3</LEVEL_>
		<CODEEMPTY>0</CODEEMPTY>
		<SELECTABLE>0</SELECTABLE>
		<DESCRIPTIONS>
			<DESCRIPTION>
				<INDEX_>1</INDEX_>
				<DESCR>Bezelye (Pisum sativum):</DESCR>
			</DESCRIPTION>
		</DESCRIPTIONS>
	</GTIP>
	<GTIP>
		<CODE>07.13.10.0</CODE>
		<LEVEL_>4</LEVEL_>
		<CODEEMPTY>1</CODEEMPTY>
		<SELECTABLE>0</SELECTABLE>
		<DESCRIPTIONS>
			<DESCRIPTION>
				<INDEX_>1</INDEX_>
				<DESCR>Tohumluk olanlar</DESCR>
			</DESCRIPTION>
		</DESCRIPTIONS>
	</GTIP>
	<GTIP>
		<CODE>07.13.10.10.00.11</CODE>
		<LEVEL_>5</LEVEL_>
		<CODEEMPTY>0</CODEEMPTY>
		<SELECTABLE>1</SELECTABLE>
		<DESCRIPTIONS>
			<DESCRIPTION>
				<INDEX_>1</INDEX_>
				<DESCR>Yem bezelyesi</DESCR>
			</DESCRIPTION>
		</DESCRIPTIONS>
	</GTIP>
	<GTIP>
		<CODE>07.13.10.10.00.19</CODE>
		<LEVEL_>5</LEVEL_>
		<CODEEMPTY>0</CODEEMPTY>
		<SELECTABLE>1</SELECTABLE>
		<DESCRIPTIONS>
			<DESCRIPTION>
				<INDEX_>1</INDEX_>
				<DESCR>Diðerleri</DESCR>
			</DESCRIPTION>
		</DESCRIPTIONS>
	</GTIP>
	<GTIP>
		<CODE>07.13.10.10.00.19.0</CODE>
		<LEVEL_>4</LEVEL_>
		<CODEEMPTY>1</CODEEMPTY>
		<SELECTABLE>0</SELECTABLE>
		<DESCRIPTIONS>
			<DESCRIPTION>
				<INDEX_>1</INDEX_>
				<DESCR>Diðerleri</DESCR>
			</DESCRIPTION>
		</DESCRIPTIONS>
	</GTIP>
	<GTIP>
		<CODE>07.13.10.90.00.11</CODE>
		<LEVEL_>5</LEVEL_>
		<CODEEMPTY>0</CODEEMPTY>
		<SELECTABLE>1</SELECTABLE>
		<DESCRIPTIONS>
			<DESCRIPTION>
				<INDEX_>1</INDEX_>
				<DESCR>Yem bezelyesi</DESCR>
			</DESCRIPTION>
		</DESCRIPTIONS>
	</GTIP>
	<GTIP>
		<CODE>07.13.10.90.00.19</CODE>
		<LEVEL_>5</LEVEL_>
		<CODEEMPTY>0</CODEEMPTY>
		<SELECTABLE>1</SELECTABLE>
		<DESCRIPTIONS>
			<DESCRIPTION>
				<INDEX_>1</INDEX_>
				<DESCR>Diðerleri</DESCR>
			</DESCRIPTION>
		</DESCRIPTIONS>
	</GTIP>
	<GTIP>
		<CODE>07.13.20</CODE>
		<LEVEL_>3</LEVEL_>
		<CODEEMPTY>0</CODEEMPTY>
		<SELECTABLE>0</SELECTABLE>
		<DESCRIPTIONS>
			<DESCRIPTION>
				<INDEX_>1</INDEX_>
				<DESCR>Nohut (garbanzos):</DESCR>
			</DESCRIPTION>
		</DESCRIPTIONS>
	</GTIP>
	<GTIP>
		<CODE>07.13.20.00.00.11</CODE>
		<LEVEL_>4</LEVEL_>
		<CODEEMPTY>0</CODEEMPTY>
		<SELECTABLE>1</SELECTABLE>
		<DESCRIPTIONS>
			<DESCRIPTION>
				<INDEX_>1</INDEX_>
				<DESCR>Tohumluk olanlar</DESCR>
			</DESCRIPTION>
		</DESCRIPTIONS>
	</GTIP>
	<GTIP>
		<CODE>07.13.20.00.00.19</CODE>
		<LEVEL_>4</LEVEL_>
		<CODEEMPTY>0</CODEEMPTY>
		<SELECTABLE>1</SELECTABLE>
		<DESCRIPTIONS>
			<DESCRIPTION>
				<INDEX_>1</INDEX_>
				<DESCR>Diðerleri</DESCR>
			</DESCRIPTION>
		</DESCRIPTIONS>
	</GTIP>
	<GTIP>
		<CODE>07.13.20.00.00.19.0</CODE>
		<LEVEL_>3</LEVEL_>
		<CODEEMPTY>1</CODEEMPTY>
		<SELECTABLE>0</SELECTABLE>
		<DESCRIPTIONS>
			<DESCRIPTION>
				<INDEX_>1</INDEX_>
				<DESCR>Fasulye (Vigna spp., Phaseolus spp.):</DESCR>
			</DESCRIPTION>
		</DESCRIPTIONS>
	</GTIP>
	<GTIP>
		<CODE>07.13.31</CODE>
		<LEVEL_>4</LEVEL_>
		<CODEEMPTY>0</CODEEMPTY>
		<SELECTABLE>0</SELECTABLE>
		<DESCRIPTIONS>
			<DESCRIPTION>
				<INDEX_>1</INDEX_>
				<DESCR>Vigna mungo (L.) Hepper veya vignaradiata (L.) wilczek türü fasulyeler</DESCR>
			</DESCRIPTION>
		</DESCRIPTIONS>
	</GTIP>
	<GTIP>
		<CODE>07.13.31.00.00.11</CODE>
		<LEVEL_>5</LEVEL_>
		<CODEEMPTY>0</CODEEMPTY>
		<SELECTABLE>1</SELECTABLE>
		<DESCRIPTIONS>
			<DESCRIPTION>
				<INDEX_>1</INDEX_>
				<DESCR>Tohumluk olanlar</DESCR>
			</DESCRIPTION>
		</DESCRIPTIONS>
	</GTIP>
	<GTIP>
		<CODE>07.13.31.00.00.19</CODE>
		<LEVEL_>5</LEVEL_>
		<CODEEMPTY>0</CODEEMPTY>
		<SELECTABLE>1</SELECTABLE>
		<DESCRIPTIONS>
			<DESCRIPTION>
				<INDEX_>1</INDEX_>
				<DESCR>Diðerleri</DESCR>
			</DESCRIPTION>
		</DESCRIPTIONS>
	</GTIP>
	<GTIP>
		<CODE>07.13.32</CODE>
		<LEVEL_>4</LEVEL_>
		<CODEEMPTY>0</CODEEMPTY>
		<SELECTABLE>0</SELECTABLE>
		<DESCRIPTIONS>
			<DESCRIPTION>
				<INDEX_>1</INDEX_>
				<DESCR>Küçük kýrmýzý (Adzuki) fasulye (Phaseolus veya Vigna angularis)</DESCR>
			</DESCRIPTION>
		</DESCRIPTIONS>
	</GTIP>
	<GTIP>
		<CODE>07.13.32.00.00.11</CODE>
		<LEVEL_>5</LEVEL_>
		<CODEEMPTY>0</CODEEMPTY>
		<SELECTABLE>1</SELECTABLE>
		<DESCRIPTIONS>
			<DESCRIPTION>
				<INDEX_>1</INDEX_>
				<DESCR>Tohumluk olanlar</DESCR>
			</DESCRIPTION>
		</DESCRIPTIONS>
	</GTIP>
	<GTIP>
		<CODE>07.13.32.00.00.19</CODE>
		<LEVEL_>5</LEVEL_>
		<CODEEMPTY>0</CODEEMPTY>
		<SELECTABLE>1</SELECTABLE>
		<DESCRIPTIONS>
			<DESCRIPTION>
				<INDEX_>1</INDEX_>
				<DESCR>Diðerleri</DESCR>
			</DESCRIPTION>
		</DESCRIPTIONS>
	</GTIP>
	<GTIP>
		<CODE>07.13.33</CODE>
		<LEVEL_>4</LEVEL_>
		<CODEEMPTY>0</CODEEMPTY>
		<SELECTABLE>0</SELECTABLE>
		<DESCRIPTIONS>
			<DESCRIPTION>
				<INDEX_>1</INDEX_>
				<DESCR>Adi fasulye (beyaz fasulye dahil) (Phaseolus vulgaris):</DESCR>
			</DESCRIPTION>
		</DESCRIPTIONS>
	</GTIP>
	<GTIP>
		<CODE>07.13.33.10.00.00</CODE>
		<LEVEL_>5</LEVEL_>
		<CODEEMPTY>0</CODEEMPTY>
		<SELECTABLE>1</SELECTABLE>
		<DESCRIPTIONS>
			<DESCRIPTION>
				<INDEX_>1</INDEX_>
				<DESCR>Tohumluk olanlar</DESCR>
			</DESCRIPTION>
		</DESCRIPTIONS>
	</GTIP>
	<GTIP>
		<CODE>07.13.33.90.00.00</CODE>
		<LEVEL_>5</LEVEL_>
		<CODEEMPTY>0</CODEEMPTY>
		<SELECTABLE>1</SELECTABLE>
		<DESCRIPTIONS>
			<DESCRIPTION>
				<INDEX_>1</INDEX_>
				<DESCR>Diðerleri</DESCR>
			</DESCRIPTION>
		</DESCRIPTIONS>
	</GTIP>
	<GTIP>
		<CODE>07.13.39</CODE>
		<LEVEL_>4</LEVEL_>
		<CODEEMPTY>0</CODEEMPTY>
		<SELECTABLE>0</SELECTABLE>
		<DESCRIPTIONS>
			<DESCRIPTION>
				<INDEX_>1</INDEX_>
				<DESCR>Diðerleri</DESCR>
			</DESCRIPTION>
		</DESCRIPTIONS>
	</GTIP>
	<GTIP>
		<CODE>07.13.39.00.00.11</CODE>
		<LEVEL_>5</LEVEL_>
		<CODEEMPTY>0</CODEEMPTY>
		<SELECTABLE>1</SELECTABLE>
		<DESCRIPTIONS>
			<DESCRIPTION>
				<INDEX_>1</INDEX_>
				<DESCR>Tohumluk olanlar</DESCR>
			</DESCRIPTION>
		</DESCRIPTIONS>
	</GTIP>
	<GTIP>
		<CODE>07.13.39.00.00.19</CODE>
		<LEVEL_>5</LEVEL_>
		<CODEEMPTY>0</CODEEMPTY>
		<SELECTABLE>1</SELECTABLE>
		<DESCRIPTIONS>
			<DESCRIPTION>
				<INDEX_>1</INDEX_>
				<DESCR>Diðerleri</DESCR>
			</DESCRIPTION>
		</DESCRIPTIONS>
	</GTIP>
	<GTIP>
		<CODE>07.13.40</CODE>
		<LEVEL_>3</LEVEL_>
		<CODEEMPTY>0</CODEEMPTY>
		<SELECTABLE>0</SELECTABLE>
		<DESCRIPTIONS>
			<DESCRIPTION>
				<INDEX_>1</INDEX_>
				<DESCR>Mercimekler</DESCR>
			</DESCRIPTION>
		</DESCRIPTIONS>
	</GTIP>
	<GTIP>
		<CODE>07.13.40.00.00.11</CODE>
		<LEVEL_>4</LEVEL_>
		<CODEEMPTY>0</CODEEMPTY>
		<SELECTABLE>1</SELECTABLE>
		<DESCRIPTIONS>
			<DESCRIPTION>
				<INDEX_>1</INDEX_>
				<DESCR>Tohumluk olanlar</DESCR>
			</DESCRIPTION>
		</DESCRIPTIONS>
	</GTIP>
	<GTIP>
		<CODE>07.13.40.00.00.12</CODE>
		<LEVEL_>4</LEVEL_>
		<CODEEMPTY>0</CODEEMPTY>
		<SELECTABLE>1</SELECTABLE>
		<DESCRIPTIONS>
			<DESCRIPTION>
				<INDEX_>1</INDEX_>
				<DESCR>Yeþil mercimek</DESCR>
			</DESCRIPTION>
		</DESCRIPTIONS>
	</GTIP>
	<GTIP>
		<CODE>07.13.40.00.00.13</CODE>
		<LEVEL_>4</LEVEL_>
		<CODEEMPTY>0</CODEEMPTY>
		<SELECTABLE>1</SELECTABLE>
		<DESCRIPTIONS>
			<DESCRIPTION>
				<INDEX_>1</INDEX_>
				<DESCR>Kýrmýzý mercimek</DESCR>
			</DESCRIPTION>
		</DESCRIPTIONS>
	</GTIP>
	<GTIP>
		<CODE>07.13.40.00.00.19</CODE>
		<LEVEL_>4</LEVEL_>
		<CODEEMPTY>0</CODEEMPTY>
		<SELECTABLE>1</SELECTABLE>
		<DESCRIPTIONS>
			<DESCRIPTION>
				<INDEX_>1</INDEX_>
				<DESCR>Diðerleri</DESCR>
			</DESCRIPTION>
		</DESCRIPTIONS>
	</GTIP>
	<GTIP>
		<CODE>07.13.50</CODE>
		<LEVEL_>3</LEVEL_>
		<CODEEMPTY>0</CODEEMPTY>
		<SELECTABLE>0</SELECTABLE>
		<DESCRIPTIONS>
			<DESCRIPTION>
				<INDEX_>1</INDEX_>
				<DESCR>Baklalar (Vicia faba var. Major) ve at baklasý (Vicia faba var. equina, Vicia faba var. minor)</DESCR>
			</DESCRIPTION>
		</DESCRIPTIONS>
	</GTIP>
	<GTIP>
		<CODE>07.13.50.00.00.11</CODE>
		<LEVEL_>4</LEVEL_>
		<CODEEMPTY>0</CODEEMPTY>
		<SELECTABLE>1</SELECTABLE>
		<DESCRIPTIONS>
			<DESCRIPTION>
				<INDEX_>1</INDEX_>
				<DESCR>Tohumluk olanlar</DESCR>
			</DESCRIPTION>
		</DESCRIPTIONS>
	</GTIP>
	<GTIP>
		<CODE>07.13.50.00.00.19</CODE>
		<LEVEL_>4</LEVEL_>
		<CODEEMPTY>0</CODEEMPTY>
		<SELECTABLE>1</SELECTABLE>
		<DESCRIPTIONS>
			<DESCRIPTION>
				<INDEX_>1</INDEX_>
				<DESCR>Diðerleri</DESCR>
			</DESCRIPTION>
		</DESCRIPTIONS>
	</GTIP>
	<GTIP>
		<CODE>07.13.90</CODE>
		<LEVEL_>3</LEVEL_>
		<CODEEMPTY>0</CODEEMPTY>
		<SELECTABLE>0</SELECTABLE>
		<DESCRIPTIONS>
			<DESCRIPTION>
				<INDEX_>1</INDEX_>
				<DESCR>Diðerleri:</DESCR>
			</DESCRIPTION>
		</DESCRIPTIONS>
	</GTIP>
	<GTIP>
		<CODE>07.13.90.00.00.11</CODE>
		<LEVEL_>4</LEVEL_>
		<CODEEMPTY>0</CODEEMPTY>
		<SELECTABLE>1</SELECTABLE>
		<DESCRIPTIONS>
			<DESCRIPTION>
				<INDEX_>1</INDEX_>
				<DESCR>Tohumluk börülce</DESCR>
			</DESCRIPTION>
		</DESCRIPTIONS>
	</GTIP>
	<GTIP>
		<CODE>07.13.90.00.00.12</CODE>
		<LEVEL_>4</LEVEL_>
		<CODEEMPTY>0</CODEEMPTY>
		<SELECTABLE>1</SELECTABLE>
		<DESCRIPTIONS>
			<DESCRIPTION>
				<INDEX_>1</INDEX_>
				<DESCR>Tohumluk barbunya</DESCR>
			</DESCRIPTION>
		</DESCRIPTIONS>
	</GTIP>
	<GTIP>
		<CODE>07.13.90.00.00.13</CODE>
		<LEVEL_>4</LEVEL_>
		<CODEEMPTY>0</CODEEMPTY>
		<SELECTABLE>1</SELECTABLE>
		<DESCRIPTIONS>
			<DESCRIPTION>
				<INDEX_>1</INDEX_>
				<DESCR>Diðer tohumluk olanlar</DESCR>
			</DESCRIPTION>
		</DESCRIPTIONS>
	</GTIP>
	<GTIP>
		<CODE>07.13.90.00.00.14</CODE>
		<LEVEL_>4</LEVEL_>
		<CODEEMPTY>0</CODEEMPTY>
		<SELECTABLE>1</SELECTABLE>
		<DESCRIPTIONS>
			<DESCRIPTION>
				<INDEX_>1</INDEX_>
				<DESCR>Börülce</DESCR>
			</DESCRIPTION>
		</DESCRIPTIONS>
	</GTIP>
	<GTIP>
		<CODE>07.13.90.00.00.15</CODE>
		<LEVEL_>4</LEVEL_>
		<CODEEMPTY>0</CODEEMPTY>
		<SELECTABLE>1</SELECTABLE>
		<DESCRIPTIONS>
			<DESCRIPTION>
				<INDEX_>1</INDEX_>
				<DESCR>Barbunya</DESCR>
			</DESCRIPTION>
		</DESCRIPTIONS>
	</GTIP>
	<GTIP>
		<CODE>07.13.90.00.00.19</CODE>
		<LEVEL_>4</LEVEL_>
		<CODEEMPTY>0</CODEEMPTY>
		<SELECTABLE>1</SELECTABLE>
		<DESCRIPTIONS>
			<DESCRIPTION>
				<INDEX_>1</INDEX_>
				<DESCR>Diðerleri</DESCR>
			</DESCRIPTION>
		</DESCRIPTIONS>
	</GTIP>
	<GTIP>
		<CODE>07.14</CODE>
		<LEVEL_>2</LEVEL_>
		<CODEEMPTY>0</CODEEMPTY>
		<SELECTABLE>0</SELECTABLE>
		<DESCRIPTIONS>
			<DESCRIPTION>
				<INDEX_>1</INDEX_>
				<DESCR>Manyok, ararot ,salep, yer elmasý ,tatlý patates ve yüksek oranda niþasta veya inülin içeren benzeri kök ve yumrular (taze , soðu- tulmuþ, dondurulmuþ</DESCR>
			</DESCRIPTION>
			<DESCRIPTION>
				<INDEX_>2</INDEX_>
				<DESCR>veya kurutulmuþ) (dilimlere ayrýlmýþ veya "pellet" þeklinde olsun olmasýn); sagu özü:</DESCR>
			</DESCRIPTION>
		</DESCRIPTIONS>
	</GTIP>
	<GTIP>
		<CODE>07.14.10</CODE>
		<LEVEL_>3</LEVEL_>
		<CODEEMPTY>0</CODEEMPTY>
		<SELECTABLE>0</SELECTABLE>
		<DESCRIPTIONS>
			<DESCRIPTION>
				<INDEX_>1</INDEX_>
				<DESCR>Manyok (cassava) :</DESCR>
			</DESCRIPTION>
		</DESCRIPTIONS>
	</GTIP>
	<GTIP>
		<CODE>07.14.10.91.00.00</CODE>
		<LEVEL_>4</LEVEL_>
		<CODEEMPTY>0</CODEEMPTY>
		<SELECTABLE>1</SELECTABLE>
		<DESCRIPTIONS>
			<DESCRIPTION>
				<INDEX_>1</INDEX_>
				<DESCR>Ýnsan gýdasý olarak kullanýlmaya elveriþli,net muhtevasý 28 kg.ý geçmeyen ambalajlarda olanlar (taze ve bütün halde veya kabuk- suz ve dondurulmuþ) (d</DESCR>
			</DESCRIPTION>
			<DESCRIPTION>
				<INDEX_>2</INDEX_>
				<DESCR>ilimlenmiþ olsun olmasýn)</DESCR>
			</DESCRIPTION>
		</DESCRIPTIONS>
	</GTIP>
	<GTIP>
		<CODE>07.14.10.98.00.00</CODE>
		<LEVEL_>4</LEVEL_>
		<CODEEMPTY>0</CODEEMPTY>
		<SELECTABLE>1</SELECTABLE>
		<DESCRIPTIONS>
			<DESCRIPTION>
				<INDEX_>1</INDEX_>
				<DESCR>Diðerleri</DESCR>
			</DESCRIPTION>
		</DESCRIPTIONS>
	</GTIP>
	<GTIP>
		<CODE>07.14.20</CODE>
		<LEVEL_>3</LEVEL_>
		<CODEEMPTY>0</CODEEMPTY>
		<SELECTABLE>0</SELECTABLE>
		<DESCRIPTIONS>
			<DESCRIPTION>
				<INDEX_>1</INDEX_>
				<DESCR>Tatlý patates:</DESCR>
			</DESCRIPTION>
		</DESCRIPTIONS>
	</GTIP>
	<GTIP>
		<CODE>07.14.20.10.00.00</CODE>
		<LEVEL_>4</LEVEL_>
		<CODEEMPTY>0</CODEEMPTY>
		<SELECTABLE>1</SELECTABLE>
		<DESCRIPTIONS>
			<DESCRIPTION>
				<INDEX_>1</INDEX_>
				<DESCR>Taze, bütün halde (insan gýdasý olarak kullanýlmaya elveriþli hale getirilmiþ)</DESCR>
			</DESCRIPTION>
		</DESCRIPTIONS>
	</GTIP>
	<GTIP>
		<CODE>07.14.20.10.00.00.0</CODE>
		<LEVEL_>4</LEVEL_>
		<CODEEMPTY>1</CODEEMPTY>
		<SELECTABLE>0</SELECTABLE>
		<DESCRIPTIONS>
			<DESCRIPTION>
				<INDEX_>1</INDEX_>
				<DESCR>Diðerleri :</DESCR>
			</DESCRIPTION>
		</DESCRIPTIONS>
	</GTIP>
	<GTIP>
		<CODE>07.14.20.90.10.00</CODE>
		<LEVEL_>5</LEVEL_>
		<CODEEMPTY>0</CODEEMPTY>
		<SELECTABLE>1</SELECTABLE>
		<DESCRIPTIONS>
			<DESCRIPTION>
				<INDEX_>1</INDEX_>
				<DESCR>Dondurulmuþ</DESCR>
			</DESCRIPTION>
		</DESCRIPTIONS>
	</GTIP>
	<GTIP>
		<CODE>07.14.20.90.90.00</CODE>
		<LEVEL_>5</LEVEL_>
		<CODEEMPTY>0</CODEEMPTY>
		<SELECTABLE>1</SELECTABLE>
		<DESCRIPTIONS>
			<DESCRIPTION>
				<INDEX_>1</INDEX_>
				<DESCR>Diðerleri</DESCR>
			</DESCRIPTION>
		</DESCRIPTIONS>
	</GTIP>
	<GTIP>
		<CODE>07.14.90</CODE>
		<LEVEL_>3</LEVEL_>
		<CODEEMPTY>0</CODEEMPTY>
		<SELECTABLE>0</SELECTABLE>
		<DESCRIPTIONS>
			<DESCRIPTION>
				<INDEX_>1</INDEX_>
				<DESCR>Diðerleri:</DESCR>
			</DESCRIPTION>
		</DESCRIPTIONS>
	</GTIP>
	<GTIP>
		<CODE>07.14.90.0</CODE>
		<LEVEL_>4</LEVEL_>
		<CODEEMPTY>1</CODEEMPTY>
		<SELECTABLE>0</SELECTABLE>
		<DESCRIPTIONS>
			<DESCRIPTION>
				<INDEX_>1</INDEX_>
				<DESCR>Ararot ve salep kökleri ve yüksek oranda niþasta veya inülin içeren benzeri kök ve yumrular:</DESCR>
			</DESCRIPTION>
		</DESCRIPTIONS>
	</GTIP>
	<GTIP>
		<CODE>07.14.90.0.0</CODE>
		<LEVEL_>5</LEVEL_>
		<CODEEMPTY>1</CODEEMPTY>
		<SELECTABLE>0</SELECTABLE>
		<DESCRIPTIONS>
			<DESCRIPTION>
				<INDEX_>1</INDEX_>
				<DESCR>Ýnsan gýdasý olarak kullanýlmaya elveriþli, net muhtevasý 28 kg.ý geçmeyen ambalajlarda olanlar (taze ve bütün halde veya kabuksuz ve dondurulmuþ) (di</DESCR>
			</DESCRIPTION>
			<DESCRIPTION>
				<INDEX_>2</INDEX_>
				<DESCR>limlenmiþ olsun olmasýn) :</DESCR>
			</DESCRIPTION>
		</DESCRIPTIONS>
	</GTIP>
	<GTIP>
		<CODE>07.14.90.11.00.11</CODE>
		<LEVEL_>6</LEVEL_>
		<CODEEMPTY>0</CODEEMPTY>
		<SELECTABLE>1</SELECTABLE>
		<DESCRIPTIONS>
			<DESCRIPTION>
				<INDEX_>1</INDEX_>
				<DESCR>Ararot</DESCR>
			</DESCRIPTION>
		</DESCRIPTIONS>
	</GTIP>
	<GTIP>
		<CODE>07.14.90.11.00.12</CODE>
		<LEVEL_>6</LEVEL_>
		<CODEEMPTY>0</CODEEMPTY>
		<SELECTABLE>1</SELECTABLE>
		<DESCRIPTIONS>
			<DESCRIPTION>
				<INDEX_>1</INDEX_>
				<DESCR>Salep</DESCR>
			</DESCRIPTION>
		</DESCRIPTIONS>
	</GTIP>
	<GTIP>
		<CODE>07.14.90.11.00.19</CODE>
		<LEVEL_>6</LEVEL_>
		<CODEEMPTY>0</CODEEMPTY>
		<SELECTABLE>1</SELECTABLE>
		<DESCRIPTIONS>
			<DESCRIPTION>
				<INDEX_>1</INDEX_>
				<DESCR>Diðerleri</DESCR>
			</DESCRIPTION>
		</DESCRIPTIONS>
	</GTIP>
	<GTIP>
		<CODE>07.14.90.11.00.19.0</CODE>
		<LEVEL_>5</LEVEL_>
		<CODEEMPTY>1</CODEEMPTY>
		<SELECTABLE>0</SELECTABLE>
		<DESCRIPTIONS>
			<DESCRIPTION>
				<INDEX_>1</INDEX_>
				<DESCR>Diðerleri</DESCR>
			</DESCRIPTION>
		</DESCRIPTIONS>
	</GTIP>
	<GTIP>
		<CODE>07.14.90.19.00.11</CODE>
		<LEVEL_>6</LEVEL_>
		<CODEEMPTY>0</CODEEMPTY>
		<SELECTABLE>1</SELECTABLE>
		<DESCRIPTIONS>
			<DESCRIPTION>
				<INDEX_>1</INDEX_>
				<DESCR>Ararot</DESCR>
			</DESCRIPTION>
		</DESCRIPTIONS>
	</GTIP>
	<GTIP>
		<CODE>07.14.90.19.00.12</CODE>
		<LEVEL_>6</LEVEL_>
		<CODEEMPTY>0</CODEEMPTY>
		<SELECTABLE>1</SELECTABLE>
		<DESCRIPTIONS>
			<DESCRIPTION>
				<INDEX_>1</INDEX_>
				<DESCR>Salep</DESCR>
			</DESCRIPTION>
		</DESCRIPTIONS>
	</GTIP>
	<GTIP>
		<CODE>07.14.90.19.00.19</CODE>
		<LEVEL_>6</LEVEL_>
		<CODEEMPTY>0</CODEEMPTY>
		<SELECTABLE>1</SELECTABLE>
		<DESCRIPTIONS>
			<DESCRIPTION>
				<INDEX_>1</INDEX_>
				<DESCR>Diðerleri</DESCR>
			</DESCRIPTION>
		</DESCRIPTIONS>
	</GTIP>
	<GTIP>
		<CODE>07.14.90.19.00.19.0</CODE>
		<LEVEL_>4</LEVEL_>
		<CODEEMPTY>1</CODEEMPTY>
		<SELECTABLE>0</SELECTABLE>
		<DESCRIPTIONS>
			<DESCRIPTION>
				<INDEX_>1</INDEX_>
				<DESCR>Diðerleri :</DESCR>
			</DESCRIPTION>
		</DESCRIPTIONS>
	</GTIP>
	<GTIP>
		<CODE>07.14.90.90.10.00</CODE>
		<LEVEL_>5</LEVEL_>
		<CODEEMPTY>0</CODEEMPTY>
		<SELECTABLE>1</SELECTABLE>
		<DESCRIPTIONS>
			<DESCRIPTION>
				<INDEX_>1</INDEX_>
				<DESCR>Dondurulmuþ</DESCR>
			</DESCRIPTION>
		</DESCRIPTIONS>
	</GTIP>
	<GTIP>
		<CODE>07.14.90.90.90.00</CODE>
		<LEVEL_>5</LEVEL_>
		<CODEEMPTY>0</CODEEMPTY>
		<SELECTABLE>1</SELECTABLE>
		<DESCRIPTIONS>
			<DESCRIPTION>
				<INDEX_>1</INDEX_>
				<DESCR>Diðerleri</DESCR>
			</DESCRIPTION>
		</DESCRIPTIONS>
	</GTIP>
</GTIPCODES>
