<?xml version="1.0" encoding="ISO-8859-9"?>
<GTIPCODES>
	<GTIP>
		<CODE>42.01.00.00.00.00</CODE>
		<LEVEL_>2</LEVEL_>
		<CODEEMPTY>0</CODEEMPTY>
		<SELECTABLE>1</SELECTABLE>
		<DESCRIPTIONS>
			<DESCRIPTION>
				<INDEX_>1</INDEX_>
				<DESCR>Her tür hayvan için saraciye eþyasý, eyer ve koþum takýmlarý (koþum kayýþlarý, yularlar, diþlikler, burunsalýklar, eyer örtüleri, eyer torbalarý, köpe</DESCR>
			</DESCRIPTION>
			<DESCRIPTION>
				<INDEX_>2</INDEX_>
				<DESCR>k elbiseleri ve benzerleri) (imal edildiði madde ne olursa olsun)</DESCR>
			</DESCRIPTION>
		</DESCRIPTIONS>
	</GTIP>
	<GTIP>
		<CODE>42.02</CODE>
		<LEVEL_>2</LEVEL_>
		<CODEEMPTY>0</CODEEMPTY>
		<SELECTABLE>0</SELECTABLE>
		<DESCRIPTIONS>
			<DESCRIPTION>
				<INDEX_>1</INDEX_>
				<DESCR>Sandýklar, bavullar, valizler, evrak çantalarý, okul çantalarý, gözlük kýlýflarý, dürbün mahfazalarý, fotoðraf makinasý mahfazasý, müzik aletleri mahf</DESCR>
			</DESCRIPTION>
			<DESCRIPTION>
				<INDEX_>2</INDEX_>
				<DESCR>azalarý, silah ve tabanca kýlýflarý ve benzeri mahfazalar; tabii veya terkip yoluyla elde edilen deri ve köseleden, plastik madde yapraklarýndan, doku</DESCR>
			</DESCRIPTION>
			<DESCRIPTION>
				<INDEX_>3</INDEX_>
				<DESCR>maya elveriþli maddelerden, vulkanize edilmiþ liflerden, kartondan yapýlmýþ veya tamamen yahut kýsmen bu maddelerle veya kaðýtla kaplanmýþ seyahat çan</DESCR>
			</DESCRIPTION>
			<DESCRIPTION>
				<INDEX_>4</INDEX_>
				<DESCR>talarý, izole edilmiþ yiyecek veya içecek torbalarý, tuvalet çantalarý,sýrt çantalarý el çantalarý, erzak çantalarý,portföyler, para keseleri, harita</DESCR>
			</DESCRIPTION>
			<DESCRIPTION>
				<INDEX_>5</INDEX_>
				<DESCR>ve kimlik mahfazalarý, sigara kutularý, tabaka ve tütün kese ve kutularý takým çantalarý, spor çantalarý, þiþe mahfazalarý, mücevher kutularý, pudra -</DESCR>
			</DESCRIPTION>
			<DESCRIPTION>
				<INDEX_>6</INDEX_>
				<DESCR>baharat -barut kutularý, býçak kýlýflarý ve benzeri mahfazalar:</DESCR>
			</DESCRIPTION>
		</DESCRIPTIONS>
	</GTIP>
	<GTIP>
		<CODE>42.02.0</CODE>
		<LEVEL_>3</LEVEL_>
		<CODEEMPTY>1</CODEEMPTY>
		<SELECTABLE>0</SELECTABLE>
		<DESCRIPTIONS>
			<DESCRIPTION>
				<INDEX_>1</INDEX_>
				<DESCR>Sandýklar, bavullar, valizler, evrak çantalarý, okul çantalarý ve benzeri mahfazalar:</DESCR>
			</DESCRIPTION>
		</DESCRIPTIONS>
	</GTIP>
	<GTIP>
		<CODE>42.02.11</CODE>
		<LEVEL_>4</LEVEL_>
		<CODEEMPTY>0</CODEEMPTY>
		<SELECTABLE>0</SELECTABLE>
		<DESCRIPTIONS>
			<DESCRIPTION>
				<INDEX_>1</INDEX_>
				<DESCR>Dýþ yüzleri tabii veya terkip yoluyla elde edilen deri ve kösele - den veya rugandan olanlar:</DESCR>
			</DESCRIPTION>
		</DESCRIPTIONS>
	</GTIP>
	<GTIP>
		<CODE>42.02.11.0</CODE>
		<LEVEL_>5</LEVEL_>
		<CODEEMPTY>1</CODEEMPTY>
		<SELECTABLE>0</SELECTABLE>
		<DESCRIPTIONS>
			<DESCRIPTION>
				<INDEX_>1</INDEX_>
				<DESCR>Evrak çantalarý, okul çantalarý ve benzeri mahfazalar</DESCR>
			</DESCRIPTION>
		</DESCRIPTIONS>
	</GTIP>
	<GTIP>
		<CODE>42.02.11.10.00.11</CODE>
		<LEVEL_>6</LEVEL_>
		<CODEEMPTY>0</CODEEMPTY>
		<SELECTABLE>1</SELECTABLE>
		<DESCRIPTIONS>
			<DESCRIPTION>
				<INDEX_>1</INDEX_>
				<DESCR>Tabii deri ve köseleden olanlar</DESCR>
			</DESCRIPTION>
		</DESCRIPTIONS>
	</GTIP>
	<GTIP>
		<CODE>42.02.11.10.00.12</CODE>
		<LEVEL_>6</LEVEL_>
		<CODEEMPTY>0</CODEEMPTY>
		<SELECTABLE>1</SELECTABLE>
		<DESCRIPTIONS>
			<DESCRIPTION>
				<INDEX_>1</INDEX_>
				<DESCR>Terkip yoluyla elde edilen deri ve köseleden olanlar</DESCR>
			</DESCRIPTION>
		</DESCRIPTIONS>
	</GTIP>
	<GTIP>
		<CODE>42.02.11.10.00.13</CODE>
		<LEVEL_>6</LEVEL_>
		<CODEEMPTY>0</CODEEMPTY>
		<SELECTABLE>1</SELECTABLE>
		<DESCRIPTIONS>
			<DESCRIPTION>
				<INDEX_>1</INDEX_>
				<DESCR>Rugandan olanlar</DESCR>
			</DESCRIPTION>
		</DESCRIPTIONS>
	</GTIP>
	<GTIP>
		<CODE>42.02.11.10.00.13.0</CODE>
		<LEVEL_>5</LEVEL_>
		<CODEEMPTY>1</CODEEMPTY>
		<SELECTABLE>0</SELECTABLE>
		<DESCRIPTIONS>
			<DESCRIPTION>
				<INDEX_>1</INDEX_>
				<DESCR>Diðerleri</DESCR>
			</DESCRIPTION>
		</DESCRIPTIONS>
	</GTIP>
	<GTIP>
		<CODE>42.02.11.90.00.11</CODE>
		<LEVEL_>6</LEVEL_>
		<CODEEMPTY>0</CODEEMPTY>
		<SELECTABLE>1</SELECTABLE>
		<DESCRIPTIONS>
			<DESCRIPTION>
				<INDEX_>1</INDEX_>
				<DESCR>Tabii deri ve köseleden olanlar</DESCR>
			</DESCRIPTION>
		</DESCRIPTIONS>
	</GTIP>
	<GTIP>
		<CODE>42.02.11.90.00.12</CODE>
		<LEVEL_>6</LEVEL_>
		<CODEEMPTY>0</CODEEMPTY>
		<SELECTABLE>1</SELECTABLE>
		<DESCRIPTIONS>
			<DESCRIPTION>
				<INDEX_>1</INDEX_>
				<DESCR>Terkip yoluyla elde edilen deri ve köseleden olanlar</DESCR>
			</DESCRIPTION>
		</DESCRIPTIONS>
	</GTIP>
	<GTIP>
		<CODE>42.02.11.90.00.13</CODE>
		<LEVEL_>6</LEVEL_>
		<CODEEMPTY>0</CODEEMPTY>
		<SELECTABLE>1</SELECTABLE>
		<DESCRIPTIONS>
			<DESCRIPTION>
				<INDEX_>1</INDEX_>
				<DESCR>Rugandan olanlar</DESCR>
			</DESCRIPTION>
		</DESCRIPTIONS>
	</GTIP>
	<GTIP>
		<CODE>42.02.12</CODE>
		<LEVEL_>4</LEVEL_>
		<CODEEMPTY>0</CODEEMPTY>
		<SELECTABLE>0</SELECTABLE>
		<DESCRIPTIONS>
			<DESCRIPTION>
				<INDEX_>1</INDEX_>
				<DESCR>Dýþ yüzleri plastikten veya dokumaya elveriþli maddelerden olanlar :</DESCR>
			</DESCRIPTION>
		</DESCRIPTIONS>
	</GTIP>
	<GTIP>
		<CODE>42.02.12.0</CODE>
		<LEVEL_>5</LEVEL_>
		<CODEEMPTY>1</CODEEMPTY>
		<SELECTABLE>0</SELECTABLE>
		<DESCRIPTIONS>
			<DESCRIPTION>
				<INDEX_>1</INDEX_>
				<DESCR>Plastik madde yapraklarýndan yapýlmýþ olanlar:</DESCR>
			</DESCRIPTION>
		</DESCRIPTIONS>
	</GTIP>
	<GTIP>
		<CODE>42.02.12.11.00.00</CODE>
		<LEVEL_>6</LEVEL_>
		<CODEEMPTY>0</CODEEMPTY>
		<SELECTABLE>1</SELECTABLE>
		<DESCRIPTIONS>
			<DESCRIPTION>
				<INDEX_>1</INDEX_>
				<DESCR>Evrak çantalarý,okul çantalarý ve benzeri mahfazalar</DESCR>
			</DESCRIPTION>
		</DESCRIPTIONS>
	</GTIP>
	<GTIP>
		<CODE>42.02.12.19.00.00</CODE>
		<LEVEL_>6</LEVEL_>
		<CODEEMPTY>0</CODEEMPTY>
		<SELECTABLE>1</SELECTABLE>
		<DESCRIPTIONS>
			<DESCRIPTION>
				<INDEX_>1</INDEX_>
				<DESCR>Diðerleri</DESCR>
			</DESCRIPTION>
		</DESCRIPTIONS>
	</GTIP>
	<GTIP>
		<CODE>42.02.12.50.00.00</CODE>
		<LEVEL_>5</LEVEL_>
		<CODEEMPTY>0</CODEEMPTY>
		<SELECTABLE>1</SELECTABLE>
		<DESCRIPTIONS>
			<DESCRIPTION>
				<INDEX_>1</INDEX_>
				<DESCR>Kalýplanmýþ plastik maddelerden yapýlmýþ olanlar</DESCR>
			</DESCRIPTION>
		</DESCRIPTIONS>
	</GTIP>
	<GTIP>
		<CODE>42.02.12.50.00.00.0</CODE>
		<LEVEL_>5</LEVEL_>
		<CODEEMPTY>1</CODEEMPTY>
		<SELECTABLE>0</SELECTABLE>
		<DESCRIPTIONS>
			<DESCRIPTION>
				<INDEX_>1</INDEX_>
				<DESCR>Diðer maddelerden yapýlmýþ olanlar (vulkanize edilmiþ liflerden yapýlmýþ olanlar dahil):</DESCR>
			</DESCRIPTION>
		</DESCRIPTIONS>
	</GTIP>
	<GTIP>
		<CODE>42.02.12.50.00.00.0.0</CODE>
		<LEVEL_>6</LEVEL_>
		<CODEEMPTY>1</CODEEMPTY>
		<SELECTABLE>0</SELECTABLE>
		<DESCRIPTIONS>
			<DESCRIPTION>
				<INDEX_>1</INDEX_>
				<DESCR>Evrak çantalarý, okul çantalarý ve benzeri mahfazalar:</DESCR>
			</DESCRIPTION>
		</DESCRIPTIONS>
	</GTIP>
	<GTIP>
		<CODE>42.02.12.91.10.00</CODE>
		<LEVEL_>7</LEVEL_>
		<CODEEMPTY>0</CODEEMPTY>
		<SELECTABLE>1</SELECTABLE>
		<DESCRIPTIONS>
			<DESCRIPTION>
				<INDEX_>1</INDEX_>
				<DESCR>Elastiki veya kauçuklu olmayan örme eþyadan olanlar</DESCR>
			</DESCRIPTION>
		</DESCRIPTIONS>
	</GTIP>
	<GTIP>
		<CODE>42.02.12.91.90.00</CODE>
		<LEVEL_>7</LEVEL_>
		<CODEEMPTY>0</CODEEMPTY>
		<SELECTABLE>1</SELECTABLE>
		<DESCRIPTIONS>
			<DESCRIPTION>
				<INDEX_>1</INDEX_>
				<DESCR>Diðerleri</DESCR>
			</DESCRIPTION>
		</DESCRIPTIONS>
	</GTIP>
	<GTIP>
		<CODE>42.02.12.91.90.00.0</CODE>
		<LEVEL_>6</LEVEL_>
		<CODEEMPTY>1</CODEEMPTY>
		<SELECTABLE>0</SELECTABLE>
		<DESCRIPTIONS>
			<DESCRIPTION>
				<INDEX_>1</INDEX_>
				<DESCR>Diðerleri:</DESCR>
			</DESCRIPTION>
		</DESCRIPTIONS>
	</GTIP>
	<GTIP>
		<CODE>42.02.12.99.10.00</CODE>
		<LEVEL_>7</LEVEL_>
		<CODEEMPTY>0</CODEEMPTY>
		<SELECTABLE>1</SELECTABLE>
		<DESCRIPTIONS>
			<DESCRIPTION>
				<INDEX_>1</INDEX_>
				<DESCR>Elastiki veya kauçuklu olmayan örme eþyadan olanlar</DESCR>
			</DESCRIPTION>
		</DESCRIPTIONS>
	</GTIP>
	<GTIP>
		<CODE>42.02.12.99.90.00</CODE>
		<LEVEL_>7</LEVEL_>
		<CODEEMPTY>0</CODEEMPTY>
		<SELECTABLE>1</SELECTABLE>
		<DESCRIPTIONS>
			<DESCRIPTION>
				<INDEX_>1</INDEX_>
				<DESCR>Diðerleri</DESCR>
			</DESCRIPTION>
		</DESCRIPTIONS>
	</GTIP>
	<GTIP>
		<CODE>42.02.19</CODE>
		<LEVEL_>4</LEVEL_>
		<CODEEMPTY>0</CODEEMPTY>
		<SELECTABLE>0</SELECTABLE>
		<DESCRIPTIONS>
			<DESCRIPTION>
				<INDEX_>1</INDEX_>
				<DESCR>Diðerleri :</DESCR>
			</DESCRIPTION>
		</DESCRIPTIONS>
	</GTIP>
	<GTIP>
		<CODE>42.02.19.10.00.00</CODE>
		<LEVEL_>5</LEVEL_>
		<CODEEMPTY>0</CODEEMPTY>
		<SELECTABLE>1</SELECTABLE>
		<DESCRIPTIONS>
			<DESCRIPTION>
				<INDEX_>1</INDEX_>
				<DESCR>Aluminyumdan olanlar</DESCR>
			</DESCRIPTION>
		</DESCRIPTIONS>
	</GTIP>
	<GTIP>
		<CODE>42.02.19.10.00.00.0</CODE>
		<LEVEL_>5</LEVEL_>
		<CODEEMPTY>1</CODEEMPTY>
		<SELECTABLE>0</SELECTABLE>
		<DESCRIPTIONS>
			<DESCRIPTION>
				<INDEX_>1</INDEX_>
				<DESCR>Diðer maddelerden olanlar:</DESCR>
			</DESCRIPTION>
		</DESCRIPTIONS>
	</GTIP>
	<GTIP>
		<CODE>42.02.19.90.10.00</CODE>
		<LEVEL_>6</LEVEL_>
		<CODEEMPTY>0</CODEEMPTY>
		<SELECTABLE>1</SELECTABLE>
		<DESCRIPTIONS>
			<DESCRIPTION>
				<INDEX_>1</INDEX_>
				<DESCR>Ahþaptan veya nikelden olanlar</DESCR>
			</DESCRIPTION>
		</DESCRIPTIONS>
	</GTIP>
	<GTIP>
		<CODE>42.02.19.90.30.00</CODE>
		<LEVEL_>6</LEVEL_>
		<CODEEMPTY>0</CODEEMPTY>
		<SELECTABLE>1</SELECTABLE>
		<DESCRIPTIONS>
			<DESCRIPTION>
				<INDEX_>1</INDEX_>
				<DESCR>Dökme demir ,demir veya çelikten veya çinkodan olanlar</DESCR>
			</DESCRIPTION>
		</DESCRIPTIONS>
	</GTIP>
	<GTIP>
		<CODE>42.02.19.90.50.00</CODE>
		<LEVEL_>6</LEVEL_>
		<CODEEMPTY>0</CODEEMPTY>
		<SELECTABLE>1</SELECTABLE>
		<DESCRIPTIONS>
			<DESCRIPTION>
				<INDEX_>1</INDEX_>
				<DESCR>Bakýrdan olanlar</DESCR>
			</DESCRIPTION>
		</DESCRIPTIONS>
	</GTIP>
	<GTIP>
		<CODE>42.02.19.90.90.00</CODE>
		<LEVEL_>6</LEVEL_>
		<CODEEMPTY>0</CODEEMPTY>
		<SELECTABLE>1</SELECTABLE>
		<DESCRIPTIONS>
			<DESCRIPTION>
				<INDEX_>1</INDEX_>
				<DESCR>Diðerleri</DESCR>
			</DESCRIPTION>
		</DESCRIPTIONS>
	</GTIP>
	<GTIP>
		<CODE>42.02.19.90.90.00.0</CODE>
		<LEVEL_>3</LEVEL_>
		<CODEEMPTY>1</CODEEMPTY>
		<SELECTABLE>0</SELECTABLE>
		<DESCRIPTIONS>
			<DESCRIPTION>
				<INDEX_>1</INDEX_>
				<DESCR>El çantalarý (omuzda taþýmak için kayýþlarý olsun olmasýn) (sapsýz olanlar dahil):</DESCR>
			</DESCRIPTION>
		</DESCRIPTIONS>
	</GTIP>
	<GTIP>
		<CODE>42.02.21.00.00.00</CODE>
		<LEVEL_>4</LEVEL_>
		<CODEEMPTY>0</CODEEMPTY>
		<SELECTABLE>1</SELECTABLE>
		<DESCRIPTIONS>
			<DESCRIPTION>
				<INDEX_>1</INDEX_>
				<DESCR>Dýþ yüzleri tabii veya terkip yoluyla elde edilen deri ve kösele - den veya rugandan olanlar</DESCR>
			</DESCRIPTION>
		</DESCRIPTIONS>
	</GTIP>
	<GTIP>
		<CODE>42.02.22</CODE>
		<LEVEL_>4</LEVEL_>
		<CODEEMPTY>0</CODEEMPTY>
		<SELECTABLE>0</SELECTABLE>
		<DESCRIPTIONS>
			<DESCRIPTION>
				<INDEX_>1</INDEX_>
				<DESCR>Dýþ yüzleri plastik madde yapraklarýndan veya dokumaya elve - riþli maddelerden olanlar:</DESCR>
			</DESCRIPTION>
		</DESCRIPTIONS>
	</GTIP>
	<GTIP>
		<CODE>42.02.22.10.00.00</CODE>
		<LEVEL_>5</LEVEL_>
		<CODEEMPTY>0</CODEEMPTY>
		<SELECTABLE>1</SELECTABLE>
		<DESCRIPTIONS>
			<DESCRIPTION>
				<INDEX_>1</INDEX_>
				<DESCR>Plastik madde yapraklarýndan yapýlmýþ olanlar</DESCR>
			</DESCRIPTION>
		</DESCRIPTIONS>
	</GTIP>
	<GTIP>
		<CODE>42.02.22.10.00.00.0</CODE>
		<LEVEL_>5</LEVEL_>
		<CODEEMPTY>1</CODEEMPTY>
		<SELECTABLE>0</SELECTABLE>
		<DESCRIPTIONS>
			<DESCRIPTION>
				<INDEX_>1</INDEX_>
				<DESCR>Dokumaya elveriþli maddelerden olanlar:</DESCR>
			</DESCRIPTION>
		</DESCRIPTIONS>
	</GTIP>
	<GTIP>
		<CODE>42.02.22.90.10.00</CODE>
		<LEVEL_>6</LEVEL_>
		<CODEEMPTY>0</CODEEMPTY>
		<SELECTABLE>1</SELECTABLE>
		<DESCRIPTIONS>
			<DESCRIPTION>
				<INDEX_>1</INDEX_>
				<DESCR>Elastiki veya kauçuklu olmayan örme eþyadan olanlar</DESCR>
			</DESCRIPTION>
		</DESCRIPTIONS>
	</GTIP>
	<GTIP>
		<CODE>42.02.22.90.90.00</CODE>
		<LEVEL_>6</LEVEL_>
		<CODEEMPTY>0</CODEEMPTY>
		<SELECTABLE>1</SELECTABLE>
		<DESCRIPTIONS>
			<DESCRIPTION>
				<INDEX_>1</INDEX_>
				<DESCR>Diðerleri</DESCR>
			</DESCRIPTION>
		</DESCRIPTIONS>
	</GTIP>
	<GTIP>
		<CODE>42.02.29.00.00.00</CODE>
		<LEVEL_>4</LEVEL_>
		<CODEEMPTY>0</CODEEMPTY>
		<SELECTABLE>1</SELECTABLE>
		<DESCRIPTIONS>
			<DESCRIPTION>
				<INDEX_>1</INDEX_>
				<DESCR>Diðerleri</DESCR>
			</DESCRIPTION>
		</DESCRIPTIONS>
	</GTIP>
	<GTIP>
		<CODE>42.02.29.00.00.00.0</CODE>
		<LEVEL_>3</LEVEL_>
		<CODEEMPTY>1</CODEEMPTY>
		<SELECTABLE>0</SELECTABLE>
		<DESCRIPTIONS>
			<DESCRIPTION>
				<INDEX_>1</INDEX_>
				<DESCR>Normal olarak cepte veya el çantasýnda taþýnan eþya:</DESCR>
			</DESCRIPTION>
		</DESCRIPTIONS>
	</GTIP>
	<GTIP>
		<CODE>42.02.31.00.00.00</CODE>
		<LEVEL_>4</LEVEL_>
		<CODEEMPTY>0</CODEEMPTY>
		<SELECTABLE>1</SELECTABLE>
		<DESCRIPTIONS>
			<DESCRIPTION>
				<INDEX_>1</INDEX_>
				<DESCR>Dýþ yüzleri tabii veya terkip yoluyla elde edilen deri ve kösele - den veya rugandan olanlar</DESCR>
			</DESCRIPTION>
		</DESCRIPTIONS>
	</GTIP>
	<GTIP>
		<CODE>42.02.32</CODE>
		<LEVEL_>4</LEVEL_>
		<CODEEMPTY>0</CODEEMPTY>
		<SELECTABLE>0</SELECTABLE>
		<DESCRIPTIONS>
			<DESCRIPTION>
				<INDEX_>1</INDEX_>
				<DESCR>Dýþ yüzleri plastik madde yapraklarýndan veya dokumaya elve - riþli maddelerden olanlar:</DESCR>
			</DESCRIPTION>
		</DESCRIPTIONS>
	</GTIP>
	<GTIP>
		<CODE>42.02.32.10.00.00</CODE>
		<LEVEL_>5</LEVEL_>
		<CODEEMPTY>0</CODEEMPTY>
		<SELECTABLE>1</SELECTABLE>
		<DESCRIPTIONS>
			<DESCRIPTION>
				<INDEX_>1</INDEX_>
				<DESCR>Plastik madde yapraklarýndan yapýlmýþ olanlar</DESCR>
			</DESCRIPTION>
		</DESCRIPTIONS>
	</GTIP>
	<GTIP>
		<CODE>42.02.32.10.00.00.0</CODE>
		<LEVEL_>5</LEVEL_>
		<CODEEMPTY>1</CODEEMPTY>
		<SELECTABLE>0</SELECTABLE>
		<DESCRIPTIONS>
			<DESCRIPTION>
				<INDEX_>1</INDEX_>
				<DESCR>Dokumaya elveriþli maddelerden olanlar:</DESCR>
			</DESCRIPTION>
		</DESCRIPTIONS>
	</GTIP>
	<GTIP>
		<CODE>42.02.32.90.10.00</CODE>
		<LEVEL_>6</LEVEL_>
		<CODEEMPTY>0</CODEEMPTY>
		<SELECTABLE>1</SELECTABLE>
		<DESCRIPTIONS>
			<DESCRIPTION>
				<INDEX_>1</INDEX_>
				<DESCR>Elastiki veya kauçuklu olmayan örme eþyadan olanlar</DESCR>
			</DESCRIPTION>
		</DESCRIPTIONS>
	</GTIP>
	<GTIP>
		<CODE>42.02.32.90.90.00</CODE>
		<LEVEL_>6</LEVEL_>
		<CODEEMPTY>0</CODEEMPTY>
		<SELECTABLE>1</SELECTABLE>
		<DESCRIPTIONS>
			<DESCRIPTION>
				<INDEX_>1</INDEX_>
				<DESCR>Diðerleri</DESCR>
			</DESCRIPTION>
		</DESCRIPTIONS>
	</GTIP>
	<GTIP>
		<CODE>42.02.39</CODE>
		<LEVEL_>4</LEVEL_>
		<CODEEMPTY>0</CODEEMPTY>
		<SELECTABLE>0</SELECTABLE>
		<DESCRIPTIONS>
			<DESCRIPTION>
				<INDEX_>1</INDEX_>
				<DESCR>Diðerleri:</DESCR>
			</DESCRIPTION>
		</DESCRIPTIONS>
	</GTIP>
	<GTIP>
		<CODE>42.02.39.00.10.00</CODE>
		<LEVEL_>5</LEVEL_>
		<CODEEMPTY>0</CODEEMPTY>
		<SELECTABLE>1</SELECTABLE>
		<DESCRIPTIONS>
			<DESCRIPTION>
				<INDEX_>1</INDEX_>
				<DESCR>Aluminyumdan, dökme demir veya çelikten veya çinkodan olanlar</DESCR>
			</DESCRIPTION>
		</DESCRIPTIONS>
	</GTIP>
	<GTIP>
		<CODE>42.02.39.00.20.00</CODE>
		<LEVEL_>5</LEVEL_>
		<CODEEMPTY>0</CODEEMPTY>
		<SELECTABLE>1</SELECTABLE>
		<DESCRIPTIONS>
			<DESCRIPTION>
				<INDEX_>1</INDEX_>
				<DESCR>Ahþap olanlar</DESCR>
			</DESCRIPTION>
		</DESCRIPTIONS>
	</GTIP>
	<GTIP>
		<CODE>42.02.39.00.30.00</CODE>
		<LEVEL_>5</LEVEL_>
		<CODEEMPTY>0</CODEEMPTY>
		<SELECTABLE>1</SELECTABLE>
		<DESCRIPTIONS>
			<DESCRIPTION>
				<INDEX_>1</INDEX_>
				<DESCR>Bakýrdan olanlar</DESCR>
			</DESCRIPTION>
		</DESCRIPTIONS>
	</GTIP>
	<GTIP>
		<CODE>42.02.39.00.40.00</CODE>
		<LEVEL_>5</LEVEL_>
		<CODEEMPTY>0</CODEEMPTY>
		<SELECTABLE>1</SELECTABLE>
		<DESCRIPTIONS>
			<DESCRIPTION>
				<INDEX_>1</INDEX_>
				<DESCR>Nikelden olanlar</DESCR>
			</DESCRIPTION>
		</DESCRIPTIONS>
	</GTIP>
	<GTIP>
		<CODE>42.02.39.00.50.00</CODE>
		<LEVEL_>5</LEVEL_>
		<CODEEMPTY>0</CODEEMPTY>
		<SELECTABLE>1</SELECTABLE>
		<DESCRIPTIONS>
			<DESCRIPTION>
				<INDEX_>1</INDEX_>
				<DESCR>Ýþlenmiþ baða, sedef, fildiþi, kemik, her nevi boynuz, mercan (tabii veya aglomere edilmiþ) ve yontulmaya elveriþli diðer hayvansal maddelerden olanla</DESCR>
			</DESCRIPTION>
			<DESCRIPTION>
				<INDEX_>2</INDEX_>
				<DESCR>r</DESCR>
			</DESCRIPTION>
		</DESCRIPTIONS>
	</GTIP>
	<GTIP>
		<CODE>42.02.39.00.60.00</CODE>
		<LEVEL_>5</LEVEL_>
		<CODEEMPTY>0</CODEEMPTY>
		<SELECTABLE>1</SELECTABLE>
		<DESCRIPTIONS>
			<DESCRIPTION>
				<INDEX_>1</INDEX_>
				<DESCR>Ýþlenmiþ yontulmaya elveriþli bitkisel ve mineral maddelerden olanlar</DESCR>
			</DESCRIPTION>
		</DESCRIPTIONS>
	</GTIP>
	<GTIP>
		<CODE>42.02.39.00.90.00</CODE>
		<LEVEL_>5</LEVEL_>
		<CODEEMPTY>0</CODEEMPTY>
		<SELECTABLE>1</SELECTABLE>
		<DESCRIPTIONS>
			<DESCRIPTION>
				<INDEX_>1</INDEX_>
				<DESCR>Diðerleri</DESCR>
			</DESCRIPTION>
		</DESCRIPTIONS>
	</GTIP>
	<GTIP>
		<CODE>42.02.39.00.90.00.0</CODE>
		<LEVEL_>3</LEVEL_>
		<CODEEMPTY>1</CODEEMPTY>
		<SELECTABLE>0</SELECTABLE>
		<DESCRIPTIONS>
			<DESCRIPTION>
				<INDEX_>1</INDEX_>
				<DESCR>Diðerleri:</DESCR>
			</DESCRIPTION>
		</DESCRIPTIONS>
	</GTIP>
	<GTIP>
		<CODE>42.02.91</CODE>
		<LEVEL_>4</LEVEL_>
		<CODEEMPTY>0</CODEEMPTY>
		<SELECTABLE>0</SELECTABLE>
		<DESCRIPTIONS>
			<DESCRIPTION>
				<INDEX_>1</INDEX_>
				<DESCR>Dýþ yüzleri tabii veya terkip yoluyla elde edilen deri ve kösele - den veya rugandan olanlar:</DESCR>
			</DESCRIPTION>
		</DESCRIPTIONS>
	</GTIP>
	<GTIP>
		<CODE>42.02.91.0</CODE>
		<LEVEL_>5</LEVEL_>
		<CODEEMPTY>1</CODEEMPTY>
		<SELECTABLE>0</SELECTABLE>
		<DESCRIPTIONS>
			<DESCRIPTION>
				<INDEX_>1</INDEX_>
				<DESCR>Seyahat çantalarý, tuvalet çantalarý, sýrt çantalarý, spor çantalarý</DESCR>
			</DESCRIPTION>
		</DESCRIPTIONS>
	</GTIP>
	<GTIP>
		<CODE>42.02.91.10.00.11</CODE>
		<LEVEL_>6</LEVEL_>
		<CODEEMPTY>0</CODEEMPTY>
		<SELECTABLE>1</SELECTABLE>
		<DESCRIPTIONS>
			<DESCRIPTION>
				<INDEX_>1</INDEX_>
				<DESCR>Tabii deri ve köseleden olanlar</DESCR>
			</DESCRIPTION>
		</DESCRIPTIONS>
	</GTIP>
	<GTIP>
		<CODE>42.02.91.10.00.12</CODE>
		<LEVEL_>6</LEVEL_>
		<CODEEMPTY>0</CODEEMPTY>
		<SELECTABLE>1</SELECTABLE>
		<DESCRIPTIONS>
			<DESCRIPTION>
				<INDEX_>1</INDEX_>
				<DESCR>Terkip yoluyla elde edilen deri ve köseleden olanlar</DESCR>
			</DESCRIPTION>
		</DESCRIPTIONS>
	</GTIP>
	<GTIP>
		<CODE>42.02.91.10.00.13</CODE>
		<LEVEL_>6</LEVEL_>
		<CODEEMPTY>0</CODEEMPTY>
		<SELECTABLE>1</SELECTABLE>
		<DESCRIPTIONS>
			<DESCRIPTION>
				<INDEX_>1</INDEX_>
				<DESCR>Rugandan olanlar</DESCR>
			</DESCRIPTION>
		</DESCRIPTIONS>
	</GTIP>
	<GTIP>
		<CODE>42.02.91.80.00.00</CODE>
		<LEVEL_>5</LEVEL_>
		<CODEEMPTY>0</CODEEMPTY>
		<SELECTABLE>1</SELECTABLE>
		<DESCRIPTIONS>
			<DESCRIPTION>
				<INDEX_>1</INDEX_>
				<DESCR>Diðerleri</DESCR>
			</DESCRIPTION>
		</DESCRIPTIONS>
	</GTIP>
	<GTIP>
		<CODE>42.02.92</CODE>
		<LEVEL_>4</LEVEL_>
		<CODEEMPTY>0</CODEEMPTY>
		<SELECTABLE>0</SELECTABLE>
		<DESCRIPTIONS>
			<DESCRIPTION>
				<INDEX_>1</INDEX_>
				<DESCR>Dýþ yüzleri plastik madde yapraklarýndan veya dokumaya elveriþli maddelerden olanlar:</DESCR>
			</DESCRIPTION>
		</DESCRIPTIONS>
	</GTIP>
	<GTIP>
		<CODE>42.02.92.0</CODE>
		<LEVEL_>5</LEVEL_>
		<CODEEMPTY>1</CODEEMPTY>
		<SELECTABLE>0</SELECTABLE>
		<DESCRIPTIONS>
			<DESCRIPTION>
				<INDEX_>1</INDEX_>
				<DESCR>Plastik madde yapraklarýndan yapýlmýþ olanlar :</DESCR>
			</DESCRIPTION>
		</DESCRIPTIONS>
	</GTIP>
	<GTIP>
		<CODE>42.02.92.11.00.00</CODE>
		<LEVEL_>6</LEVEL_>
		<CODEEMPTY>0</CODEEMPTY>
		<SELECTABLE>1</SELECTABLE>
		<DESCRIPTIONS>
			<DESCRIPTION>
				<INDEX_>1</INDEX_>
				<DESCR>Seyahat çantalarý, tuvalet çantalarý, sýrt çantalarý,spor çantalarý</DESCR>
			</DESCRIPTION>
		</DESCRIPTIONS>
	</GTIP>
	<GTIP>
		<CODE>42.02.92.15.00.00</CODE>
		<LEVEL_>6</LEVEL_>
		<CODEEMPTY>0</CODEEMPTY>
		<SELECTABLE>1</SELECTABLE>
		<DESCRIPTIONS>
			<DESCRIPTION>
				<INDEX_>1</INDEX_>
				<DESCR>Müzik aletleri mahfazalarý</DESCR>
			</DESCRIPTION>
		</DESCRIPTIONS>
	</GTIP>
	<GTIP>
		<CODE>42.02.92.19.00.00</CODE>
		<LEVEL_>6</LEVEL_>
		<CODEEMPTY>0</CODEEMPTY>
		<SELECTABLE>1</SELECTABLE>
		<DESCRIPTIONS>
			<DESCRIPTION>
				<INDEX_>1</INDEX_>
				<DESCR>Diðerleri</DESCR>
			</DESCRIPTION>
		</DESCRIPTIONS>
	</GTIP>
	<GTIP>
		<CODE>42.02.92.19.00.00.0</CODE>
		<LEVEL_>5</LEVEL_>
		<CODEEMPTY>1</CODEEMPTY>
		<SELECTABLE>0</SELECTABLE>
		<DESCRIPTIONS>
			<DESCRIPTION>
				<INDEX_>1</INDEX_>
				<DESCR>Dokumaya elveriþli maddelerden olanlar:</DESCR>
			</DESCRIPTION>
		</DESCRIPTIONS>
	</GTIP>
	<GTIP>
		<CODE>42.02.92.19.00.00.0.0</CODE>
		<LEVEL_>6</LEVEL_>
		<CODEEMPTY>1</CODEEMPTY>
		<SELECTABLE>0</SELECTABLE>
		<DESCRIPTIONS>
			<DESCRIPTION>
				<INDEX_>1</INDEX_>
				<DESCR>Seyahat çantalarý, tuvalet çantalarý, sýrt çantalarý,spor çantalarý :</DESCR>
			</DESCRIPTION>
		</DESCRIPTIONS>
	</GTIP>
	<GTIP>
		<CODE>42.02.92.91.10.00</CODE>
		<LEVEL_>7</LEVEL_>
		<CODEEMPTY>0</CODEEMPTY>
		<SELECTABLE>1</SELECTABLE>
		<DESCRIPTIONS>
			<DESCRIPTION>
				<INDEX_>1</INDEX_>
				<DESCR>Elastiki veya kauçuklu olmayan örme eþyadan ve mensucattan olanlar</DESCR>
			</DESCRIPTION>
		</DESCRIPTIONS>
	</GTIP>
	<GTIP>
		<CODE>42.02.92.91.90.00</CODE>
		<LEVEL_>7</LEVEL_>
		<CODEEMPTY>0</CODEEMPTY>
		<SELECTABLE>1</SELECTABLE>
		<DESCRIPTIONS>
			<DESCRIPTION>
				<INDEX_>1</INDEX_>
				<DESCR>Diðerleri</DESCR>
			</DESCRIPTION>
		</DESCRIPTIONS>
	</GTIP>
	<GTIP>
		<CODE>42.02.92.91.90.00.0</CODE>
		<LEVEL_>6</LEVEL_>
		<CODEEMPTY>1</CODEEMPTY>
		<SELECTABLE>0</SELECTABLE>
		<DESCRIPTIONS>
			<DESCRIPTION>
				<INDEX_>1</INDEX_>
				<DESCR>Diðerleri:</DESCR>
			</DESCRIPTION>
		</DESCRIPTIONS>
	</GTIP>
	<GTIP>
		<CODE>42.02.92.98.10.00</CODE>
		<LEVEL_>7</LEVEL_>
		<CODEEMPTY>0</CODEEMPTY>
		<SELECTABLE>1</SELECTABLE>
		<DESCRIPTIONS>
			<DESCRIPTION>
				<INDEX_>1</INDEX_>
				<DESCR>Elastiki veya kauçuklu olmayan örme eþyadan ve mensucattan olanlar</DESCR>
			</DESCRIPTION>
		</DESCRIPTIONS>
	</GTIP>
	<GTIP>
		<CODE>42.02.92.98.90.00</CODE>
		<LEVEL_>7</LEVEL_>
		<CODEEMPTY>0</CODEEMPTY>
		<SELECTABLE>1</SELECTABLE>
		<DESCRIPTIONS>
			<DESCRIPTION>
				<INDEX_>1</INDEX_>
				<DESCR>Diðerleri</DESCR>
			</DESCRIPTION>
		</DESCRIPTIONS>
	</GTIP>
	<GTIP>
		<CODE>42.02.99</CODE>
		<LEVEL_>4</LEVEL_>
		<CODEEMPTY>0</CODEEMPTY>
		<SELECTABLE>0</SELECTABLE>
		<DESCRIPTIONS>
			<DESCRIPTION>
				<INDEX_>1</INDEX_>
				<DESCR>Diðerleri:</DESCR>
			</DESCRIPTION>
		</DESCRIPTIONS>
	</GTIP>
	<GTIP>
		<CODE>42.02.99.00.10.00</CODE>
		<LEVEL_>5</LEVEL_>
		<CODEEMPTY>0</CODEEMPTY>
		<SELECTABLE>1</SELECTABLE>
		<DESCRIPTIONS>
			<DESCRIPTION>
				<INDEX_>1</INDEX_>
				<DESCR>Aluminyumdan, dökme demir veya çelikten veya çinkodan olanlar</DESCR>
			</DESCRIPTION>
		</DESCRIPTIONS>
	</GTIP>
	<GTIP>
		<CODE>42.02.99.00.20.00</CODE>
		<LEVEL_>5</LEVEL_>
		<CODEEMPTY>0</CODEEMPTY>
		<SELECTABLE>1</SELECTABLE>
		<DESCRIPTIONS>
			<DESCRIPTION>
				<INDEX_>1</INDEX_>
				<DESCR>Ahþap olanlar</DESCR>
			</DESCRIPTION>
		</DESCRIPTIONS>
	</GTIP>
	<GTIP>
		<CODE>42.02.99.00.30.00</CODE>
		<LEVEL_>5</LEVEL_>
		<CODEEMPTY>0</CODEEMPTY>
		<SELECTABLE>1</SELECTABLE>
		<DESCRIPTIONS>
			<DESCRIPTION>
				<INDEX_>1</INDEX_>
				<DESCR>Bakýrdan olanlar</DESCR>
			</DESCRIPTION>
		</DESCRIPTIONS>
	</GTIP>
	<GTIP>
		<CODE>42.02.99.00.40.00</CODE>
		<LEVEL_>5</LEVEL_>
		<CODEEMPTY>0</CODEEMPTY>
		<SELECTABLE>1</SELECTABLE>
		<DESCRIPTIONS>
			<DESCRIPTION>
				<INDEX_>1</INDEX_>
				<DESCR>Nikelden olanlar</DESCR>
			</DESCRIPTION>
		</DESCRIPTIONS>
	</GTIP>
	<GTIP>
		<CODE>42.02.99.00.50.00</CODE>
		<LEVEL_>5</LEVEL_>
		<CODEEMPTY>0</CODEEMPTY>
		<SELECTABLE>1</SELECTABLE>
		<DESCRIPTIONS>
			<DESCRIPTION>
				<INDEX_>1</INDEX_>
				<DESCR>Ýþlenmiþ baða, sedef, fildiþi, kemik, her nevi boynuz, mercan (tabii veya aglomere edilmiþ) ve yontulmaya elveriþli diðer hayvansal maddelerden olanla</DESCR>
			</DESCRIPTION>
			<DESCRIPTION>
				<INDEX_>2</INDEX_>
				<DESCR>r</DESCR>
			</DESCRIPTION>
		</DESCRIPTIONS>
	</GTIP>
	<GTIP>
		<CODE>42.02.99.00.60.00</CODE>
		<LEVEL_>5</LEVEL_>
		<CODEEMPTY>0</CODEEMPTY>
		<SELECTABLE>1</SELECTABLE>
		<DESCRIPTIONS>
			<DESCRIPTION>
				<INDEX_>1</INDEX_>
				<DESCR>Ýþlenmiþ yontulmaya elveriþli bitkisel ve mineral maddelerden olanlar</DESCR>
			</DESCRIPTION>
		</DESCRIPTIONS>
	</GTIP>
	<GTIP>
		<CODE>42.02.99.00.90.00</CODE>
		<LEVEL_>5</LEVEL_>
		<CODEEMPTY>0</CODEEMPTY>
		<SELECTABLE>1</SELECTABLE>
		<DESCRIPTIONS>
			<DESCRIPTION>
				<INDEX_>1</INDEX_>
				<DESCR>Diðerleri</DESCR>
			</DESCRIPTION>
		</DESCRIPTIONS>
	</GTIP>
	<GTIP>
		<CODE>42.03</CODE>
		<LEVEL_>2</LEVEL_>
		<CODEEMPTY>0</CODEEMPTY>
		<SELECTABLE>0</SELECTABLE>
		<DESCRIPTIONS>
			<DESCRIPTION>
				<INDEX_>1</INDEX_>
				<DESCR>Tabii veya terkip yoluyla elde edilen deri ve köseleden giyim eþyasý ve aksesuarý:</DESCR>
			</DESCRIPTION>
		</DESCRIPTIONS>
	</GTIP>
	<GTIP>
		<CODE>42.03.10</CODE>
		<LEVEL_>3</LEVEL_>
		<CODEEMPTY>0</CODEEMPTY>
		<SELECTABLE>0</SELECTABLE>
		<DESCRIPTIONS>
			<DESCRIPTION>
				<INDEX_>1</INDEX_>
				<DESCR>Giyim eþyasý</DESCR>
			</DESCRIPTION>
		</DESCRIPTIONS>
	</GTIP>
	<GTIP>
		<CODE>42.03.10.00.00.12</CODE>
		<LEVEL_>4</LEVEL_>
		<CODEEMPTY>0</CODEEMPTY>
		<SELECTABLE>1</SELECTABLE>
		<DESCRIPTIONS>
			<DESCRIPTION>
				<INDEX_>1</INDEX_>
				<DESCR>Terkip yoluyla elde edilen deri ve köseleden olanlar</DESCR>
			</DESCRIPTION>
		</DESCRIPTIONS>
	</GTIP>
	<GTIP>
		<CODE>42.03.10.00.00.19</CODE>
		<LEVEL_>4</LEVEL_>
		<CODEEMPTY>0</CODEEMPTY>
		<SELECTABLE>1</SELECTABLE>
		<DESCRIPTIONS>
			<DESCRIPTION>
				<INDEX_>1</INDEX_>
				<DESCR>Diðerleri</DESCR>
			</DESCRIPTION>
		</DESCRIPTIONS>
	</GTIP>
	<GTIP>
		<CODE>42.03.10.00.00.19.0</CODE>
		<LEVEL_>3</LEVEL_>
		<CODEEMPTY>1</CODEEMPTY>
		<SELECTABLE>0</SELECTABLE>
		<DESCRIPTIONS>
			<DESCRIPTION>
				<INDEX_>1</INDEX_>
				<DESCR>Eldivenler, tek parmaklý eldivenler, parmaksýz eldivenler:</DESCR>
			</DESCRIPTION>
		</DESCRIPTIONS>
	</GTIP>
	<GTIP>
		<CODE>42.03.21</CODE>
		<LEVEL_>4</LEVEL_>
		<CODEEMPTY>0</CODEEMPTY>
		<SELECTABLE>0</SELECTABLE>
		<DESCRIPTIONS>
			<DESCRIPTION>
				<INDEX_>1</INDEX_>
				<DESCR>Spor eldivenleri</DESCR>
			</DESCRIPTION>
		</DESCRIPTIONS>
	</GTIP>
	<GTIP>
		<CODE>42.03.21.00.00.11</CODE>
		<LEVEL_>5</LEVEL_>
		<CODEEMPTY>0</CODEEMPTY>
		<SELECTABLE>1</SELECTABLE>
		<DESCRIPTIONS>
			<DESCRIPTION>
				<INDEX_>1</INDEX_>
				<DESCR>Tabii deri ve köseleden olanlar</DESCR>
			</DESCRIPTION>
		</DESCRIPTIONS>
	</GTIP>
	<GTIP>
		<CODE>42.03.21.00.00.12</CODE>
		<LEVEL_>5</LEVEL_>
		<CODEEMPTY>0</CODEEMPTY>
		<SELECTABLE>1</SELECTABLE>
		<DESCRIPTIONS>
			<DESCRIPTION>
				<INDEX_>1</INDEX_>
				<DESCR>Terkip yoluyla elde edilen deri ve köseleden olanlar</DESCR>
			</DESCRIPTION>
		</DESCRIPTIONS>
	</GTIP>
	<GTIP>
		<CODE>42.03.29</CODE>
		<LEVEL_>4</LEVEL_>
		<CODEEMPTY>0</CODEEMPTY>
		<SELECTABLE>0</SELECTABLE>
		<DESCRIPTIONS>
			<DESCRIPTION>
				<INDEX_>1</INDEX_>
				<DESCR>Diðerleri:</DESCR>
			</DESCRIPTION>
		</DESCRIPTIONS>
	</GTIP>
	<GTIP>
		<CODE>42.03.29.0</CODE>
		<LEVEL_>5</LEVEL_>
		<CODEEMPTY>1</CODEEMPTY>
		<SELECTABLE>0</SELECTABLE>
		<DESCRIPTIONS>
			<DESCRIPTION>
				<INDEX_>1</INDEX_>
				<DESCR>Her türlü sanat ve meslek erbabýnýn korunmak amacýyla kullandýklarý eldivenler</DESCR>
			</DESCRIPTION>
		</DESCRIPTIONS>
	</GTIP>
	<GTIP>
		<CODE>42.03.29.10.00.11</CODE>
		<LEVEL_>6</LEVEL_>
		<CODEEMPTY>0</CODEEMPTY>
		<SELECTABLE>1</SELECTABLE>
		<DESCRIPTIONS>
			<DESCRIPTION>
				<INDEX_>1</INDEX_>
				<DESCR>Tabii deri ve köseleden olanlar</DESCR>
			</DESCRIPTION>
		</DESCRIPTIONS>
	</GTIP>
	<GTIP>
		<CODE>42.03.29.10.00.12</CODE>
		<LEVEL_>6</LEVEL_>
		<CODEEMPTY>0</CODEEMPTY>
		<SELECTABLE>1</SELECTABLE>
		<DESCRIPTIONS>
			<DESCRIPTION>
				<INDEX_>1</INDEX_>
				<DESCR>Terkip yoluyla elde edilen deri ve köseleden olanlar</DESCR>
			</DESCRIPTION>
		</DESCRIPTIONS>
	</GTIP>
	<GTIP>
		<CODE>42.03.29.10.00.12.0</CODE>
		<LEVEL_>5</LEVEL_>
		<CODEEMPTY>1</CODEEMPTY>
		<SELECTABLE>0</SELECTABLE>
		<DESCRIPTIONS>
			<DESCRIPTION>
				<INDEX_>1</INDEX_>
				<DESCR>Diðerleri:</DESCR>
			</DESCRIPTION>
		</DESCRIPTIONS>
	</GTIP>
	<GTIP>
		<CODE>42.03.29.91.00.00</CODE>
		<LEVEL_>6</LEVEL_>
		<CODEEMPTY>0</CODEEMPTY>
		<SELECTABLE>1</SELECTABLE>
		<DESCRIPTIONS>
			<DESCRIPTION>
				<INDEX_>1</INDEX_>
				<DESCR>Erkeklere ve erkek çocuklara ait olanlar</DESCR>
			</DESCRIPTION>
		</DESCRIPTIONS>
	</GTIP>
	<GTIP>
		<CODE>42.03.29.99.00.00</CODE>
		<LEVEL_>6</LEVEL_>
		<CODEEMPTY>0</CODEEMPTY>
		<SELECTABLE>1</SELECTABLE>
		<DESCRIPTIONS>
			<DESCRIPTION>
				<INDEX_>1</INDEX_>
				<DESCR>Diðerleri</DESCR>
			</DESCRIPTION>
		</DESCRIPTIONS>
	</GTIP>
	<GTIP>
		<CODE>42.03.30</CODE>
		<LEVEL_>3</LEVEL_>
		<CODEEMPTY>0</CODEEMPTY>
		<SELECTABLE>0</SELECTABLE>
		<DESCRIPTIONS>
			<DESCRIPTION>
				<INDEX_>1</INDEX_>
				<DESCR>Bel kemerleri, kýlýç kayýþý ve palaskalarý</DESCR>
			</DESCRIPTION>
		</DESCRIPTIONS>
	</GTIP>
	<GTIP>
		<CODE>42.03.30.00.00.11</CODE>
		<LEVEL_>4</LEVEL_>
		<CODEEMPTY>0</CODEEMPTY>
		<SELECTABLE>1</SELECTABLE>
		<DESCRIPTIONS>
			<DESCRIPTION>
				<INDEX_>1</INDEX_>
				<DESCR>Tabii deri ve köseleden olanlar</DESCR>
			</DESCRIPTION>
		</DESCRIPTIONS>
	</GTIP>
	<GTIP>
		<CODE>42.03.30.00.00.12</CODE>
		<LEVEL_>4</LEVEL_>
		<CODEEMPTY>0</CODEEMPTY>
		<SELECTABLE>1</SELECTABLE>
		<DESCRIPTIONS>
			<DESCRIPTION>
				<INDEX_>1</INDEX_>
				<DESCR>Terkip yoluyla elde edilen deri ve köseleden olanlar</DESCR>
			</DESCRIPTION>
		</DESCRIPTIONS>
	</GTIP>
	<GTIP>
		<CODE>42.03.40</CODE>
		<LEVEL_>3</LEVEL_>
		<CODEEMPTY>0</CODEEMPTY>
		<SELECTABLE>0</SELECTABLE>
		<DESCRIPTIONS>
			<DESCRIPTION>
				<INDEX_>1</INDEX_>
				<DESCR>Giyim eþyasýnýn diðer aksesuarý</DESCR>
			</DESCRIPTION>
		</DESCRIPTIONS>
	</GTIP>
	<GTIP>
		<CODE>42.03.40.00.00.11</CODE>
		<LEVEL_>4</LEVEL_>
		<CODEEMPTY>0</CODEEMPTY>
		<SELECTABLE>1</SELECTABLE>
		<DESCRIPTIONS>
			<DESCRIPTION>
				<INDEX_>1</INDEX_>
				<DESCR>Tabii deri ve köseleden olanlar</DESCR>
			</DESCRIPTION>
		</DESCRIPTIONS>
	</GTIP>
	<GTIP>
		<CODE>42.03.40.00.00.12</CODE>
		<LEVEL_>4</LEVEL_>
		<CODEEMPTY>0</CODEEMPTY>
		<SELECTABLE>1</SELECTABLE>
		<DESCRIPTIONS>
			<DESCRIPTION>
				<INDEX_>1</INDEX_>
				<DESCR>Terkip yoluyla elde edilen deri ve köseleden olanlar</DESCR>
			</DESCRIPTION>
		</DESCRIPTIONS>
	</GTIP>
	<GTIP>
		<CODE>42.05.00</CODE>
		<LEVEL_>2</LEVEL_>
		<CODEEMPTY>0</CODEEMPTY>
		<SELECTABLE>0</SELECTABLE>
		<DESCRIPTIONS>
			<DESCRIPTION>
				<INDEX_>1</INDEX_>
				<DESCR>Tabii veya terkip yoluyla elde edilen deri ve köseleden diðer eþya</DESCR>
			</DESCRIPTION>
		</DESCRIPTIONS>
	</GTIP>
	<GTIP>
		<CODE>42.05.00.0</CODE>
		<LEVEL_>3</LEVEL_>
		<CODEEMPTY>1</CODEEMPTY>
		<SELECTABLE>0</SELECTABLE>
		<DESCRIPTIONS>
			<DESCRIPTION>
				<INDEX_>1</INDEX_>
				<DESCR>Makinalarda veya mekanik aletlerde veya diðer teknik amaçlarla kulllanýlan türde olanlar:</DESCR>
			</DESCRIPTION>
		</DESCRIPTIONS>
	</GTIP>
	<GTIP>
		<CODE>42.05.00.0.0</CODE>
		<LEVEL_>4</LEVEL_>
		<CODEEMPTY>1</CODEEMPTY>
		<SELECTABLE>0</SELECTABLE>
		<DESCRIPTIONS>
			<DESCRIPTION>
				<INDEX_>1</INDEX_>
				<DESCR>Transmisyon kolanlarý ve taþýyýcý kolanlar</DESCR>
			</DESCRIPTION>
		</DESCRIPTIONS>
	</GTIP>
	<GTIP>
		<CODE>42.05.00.11.10.00</CODE>
		<LEVEL_>5</LEVEL_>
		<CODEEMPTY>0</CODEEMPTY>
		<SELECTABLE>1</SELECTABLE>
		<DESCRIPTIONS>
			<DESCRIPTION>
				<INDEX_>1</INDEX_>
				<DESCR>Transmisyon kolanlarý</DESCR>
			</DESCRIPTION>
		</DESCRIPTIONS>
	</GTIP>
	<GTIP>
		<CODE>42.05.00.11.20.00</CODE>
		<LEVEL_>5</LEVEL_>
		<CODEEMPTY>0</CODEEMPTY>
		<SELECTABLE>1</SELECTABLE>
		<DESCRIPTIONS>
			<DESCRIPTION>
				<INDEX_>1</INDEX_>
				<DESCR>Taþýyýcý kolanlar</DESCR>
			</DESCRIPTION>
		</DESCRIPTIONS>
	</GTIP>
	<GTIP>
		<CODE>42.05.00.11.20.00.0</CODE>
		<LEVEL_>4</LEVEL_>
		<CODEEMPTY>1</CODEEMPTY>
		<SELECTABLE>0</SELECTABLE>
		<DESCRIPTIONS>
			<DESCRIPTION>
				<INDEX_>1</INDEX_>
				<DESCR>Diðerleri</DESCR>
			</DESCRIPTION>
		</DESCRIPTIONS>
	</GTIP>
	<GTIP>
		<CODE>42.05.00.19.10.00</CODE>
		<LEVEL_>5</LEVEL_>
		<CODEEMPTY>0</CODEEMPTY>
		<SELECTABLE>1</SELECTABLE>
		<DESCRIPTIONS>
			<DESCRIPTION>
				<INDEX_>1</INDEX_>
				<DESCR>Makinalarda kullanýlan eþya ve dokuma sanayii için takeler (taquet)</DESCR>
			</DESCRIPTION>
		</DESCRIPTIONS>
	</GTIP>
	<GTIP>
		<CODE>42.05.00.19.90.00</CODE>
		<LEVEL_>5</LEVEL_>
		<CODEEMPTY>0</CODEEMPTY>
		<SELECTABLE>1</SELECTABLE>
		<DESCRIPTIONS>
			<DESCRIPTION>
				<INDEX_>1</INDEX_>
				<DESCR>Diðerleri</DESCR>
			</DESCRIPTION>
		</DESCRIPTIONS>
	</GTIP>
	<GTIP>
		<CODE>42.05.00.19.90.00.0</CODE>
		<LEVEL_>3</LEVEL_>
		<CODEEMPTY>1</CODEEMPTY>
		<SELECTABLE>0</SELECTABLE>
		<DESCRIPTIONS>
			<DESCRIPTION>
				<INDEX_>1</INDEX_>
				<DESCR>Diðerleri</DESCR>
			</DESCRIPTION>
		</DESCRIPTIONS>
	</GTIP>
	<GTIP>
		<CODE>42.05.00.90.00.11</CODE>
		<LEVEL_>4</LEVEL_>
		<CODEEMPTY>0</CODEEMPTY>
		<SELECTABLE>1</SELECTABLE>
		<DESCRIPTIONS>
			<DESCRIPTION>
				<INDEX_>1</INDEX_>
				<DESCR>Tabii deri veya köseleden diðer eþya</DESCR>
			</DESCRIPTION>
		</DESCRIPTIONS>
	</GTIP>
	<GTIP>
		<CODE>42.05.00.90.00.12</CODE>
		<LEVEL_>4</LEVEL_>
		<CODEEMPTY>0</CODEEMPTY>
		<SELECTABLE>1</SELECTABLE>
		<DESCRIPTIONS>
			<DESCRIPTION>
				<INDEX_>1</INDEX_>
				<DESCR>Terkip yoluyla elde edilen deri ve köseleden diðer eþya</DESCR>
			</DESCRIPTION>
		</DESCRIPTIONS>
	</GTIP>
	<GTIP>
		<CODE>42.06.00.00.00.00</CODE>
		<LEVEL_>2</LEVEL_>
		<CODEEMPTY>0</CODEEMPTY>
		<SELECTABLE>1</SELECTABLE>
		<DESCRIPTIONS>
			<DESCRIPTION>
				<INDEX_>1</INDEX_>
				<DESCR>Baðýrsak (ipek böceði guddesi hariç), kursak, mesane ve veterden mamul eþya</DESCR>
			</DESCRIPTION>
		</DESCRIPTIONS>
	</GTIP>
</GTIPCODES>
